DUT/HoldLED.v

module HoldLED #(parameter length= 250_000_000)(
	input clk,reset,
	output reg LED
	);
	
	reg [27:0] counter;
	
	always @(posedge clk)begin
		if(reset) begin
			counter<=0;
			LED <=1;
			

		end else if(counter<length)begin
			LED<=1;
			counter<= counter+1;
		end else begin
			LED<=0;
		end
		
	end
endmodule

DUT/PinCheck.v


module PinCheck #(parameter passkey = 4'b1010)(
    input [1:0] digit,
    input submit, reset, clk,
    output reg waiting, correct, incorrect,bug
);
    reg [2:0] state;
	reg update,verify;
	reg [2:0] dig_count;
	reg [7:0] password;
	reg firstDigit,secondDigit;
	reg right_wrong_in,right_wrong_out;
	 
//Instantiate LED holding
	 HoldLED holdLED(
		.clk(clk),
		.reset(right_wrong_in),
		.LED(right_wrong_out)
	 );

 //state reset
		always @(posedge clk or posedge reset) begin
		  if(reset) begin
				state <= 0;
				correct<=0;
				incorrect<=0;
				bug<=0;
		  end
		end
		
//pinloading
		always @(posedge clk) begin
			if(reset) begin
				password <= 0;
				update<=0;
				dig_count<=0;
				verify<=0;
			end else if(firstDigit) begin
				password <= {password[6:0],digit[1]};
				secondDigit<=1;
				firstDigit<=0;
			end else if(secondDigit) begin
				password <= {password[6:0],digit[0]};
				secondDigit<=0;
				dig_count<= dig_count+1;
				update<=1;
			end else if (submit) begin
				firstDigit<=1;
			end
		end


//fsm logic
		always @(posedge clk or posedge reset) begin
		  case(state)
			0:begin//Default state
				waiting<=1;
				state <= update;
				verify<=0;
			end
			1:begin//Digit read state
				if(dig_count==4) begin//if all digits are read, move to next state
					update <= 2;
					waiting<=0;
					verify<=1;
				end else begin
					update<=0;
				end
				state <=update;		
			end
			2:begin//all digits have been read, 
			//TODO: verified timing logic with timing chart, need to decide what state 2 is.
			//Next step would be verification so i need to think about what verification logic will be and how it should relate to flags like waiting or other leds
			//waiting turns to 0 when update is assigned 2. Is this ideal? state only changes 2 cycles after update changes this should be considered.
				if(password == passkey) begin
					state <=3;
				end else begin
					state<=4;
				end
				verify<=0;
			end
			
			3:begin//correct password
				right_wrong_in<=1;
				correct<=1;
				state<=5;
				
			end
			
			4:begin//incorrect password
				right_wrong_in<=1;
				incorrect<=1;
				state<=5;
			end
			
			5:begin//Holding LED
				right_wrong_in<=0;
				if(right_wrong_out!=1) begin
					state<=0;
					correct<=0;
					incorrect<=0;
				end
					
			end
			
			default:begin
				bug<=1;
			end
		  endcase
		end


    
    

    

endmodule

DUT/Encoder.v
module priorityEncoder(
	input [3:0] in,
	output reg [1:0] out
	);
	
	
	always @(*)begin
      casez(in)
		4'b1???:out=3;
		4'b01??:out=2;
		4'b001?:out=1;
		4'b0001:out=0;
		default:begin
			out=1'bx;
			end
		endcase
	end
	
endmodule

DUT/DebitPin.v


module DebitPin #(parameter passkey = 4'b1010)(
    input [3:0] digit_switches,
    input clk, reset, submit,
    output reg waiting, correct, incorrect,bug
);

    wire [1:0] digit;

    priorityEncoder priority_enc(
        .in(digit_switches),
        .out(digit)

    );

    PinCheck pinchk(
        .digit(digit),
        .submit(submit), .reset(reset), .clk(clk),
        .waiting(waiting), .correct(correct), .incorrect(incorrect),.bug(bug)
    );


endmodule

Testbench/tb_DebitPin/tb_top.sv
`ifndef passkey
    `define passkey  4'b1010
`endif


//Iverilog doesn't support constraints and random variable type :(
// class digit_item;

//     randc bit [3:0] digit;

//     constraint digit_lim {((digit == 4'b1000)||(digit == 4'b0100)||(digit == 4'b0010)||(digit == 4'b0001));}

//     function void print(string tag="");
//         $display("T=%0t [%s] digit=%0d",$time,digit);
//     endfunction
// endclass

module top();

    parameter passkey = `passkey;

    logic [3:0] digits;
    logic clk, reset, submit, waiting, correct, incorrect, bug;
    

    DebitPin #(passkey) debitpin(
        .digit_switches(digits),
        .clk(clk),
        .reset(reset),
        .submit(submit),
        .waiting(waiting),
        .correct(correct),
        .incorrect(incorrect),
        .bug(bug)
    );


    task DigitSubmission();//implement this testbench
        static bit [3:0] allowed_digits [0:3];
        logic [15:0] password;
        begin
            
            allowed_digits[0] = 4'b1000;
            allowed_digits[1] = 4'b0100;
            allowed_digits[2] = 4'b0010;
            allowed_digits[3] = 4'b0001;
            //for each digit
            repeat(24) begin
                password = 16'b0;

                repeat(4) begin
                    //randomize passkey selection
                    bit [3:0] digit;
                    digit = allowed_digits[$urandom_range(0, 3)];

                    //Track digits submitted
                    password = {password[11:0],digit};

                    //submit random digit
                    digits = digit;
                    @(posedge clk);
                        submit = 1;
                    @(negedge clk);
                        submit = 0;
                    //observe statemachine progression
                    $display("T=%0t,Sumbit = %0b,digits=%0b",$time,submit,digits);
                end
                assert(password ==debitpin.pinchk.password);
            end
        end

    endtask


    initial begin
        clk = 0;
        forever #5 clk = ~clk;
    end

    initial begin
        $dumpfile("dump.vcd");
        $dumpvars(1);

        @(negedge clk);
            reset = 1;
        @(negedge clk);
            reset = 0;

        DigitSubmission();


        $finish();
    end

endmodule

dump.vcd
$date
	Thu Aug 07 20:24:39 2025
$end
$version
	Icarus Verilog
$end
$timescale
	1s
$end
$scope module top $end
$var wire 1 ! waiting $end
$var wire 1 " incorrect $end
$var wire 1 # correct $end
$var wire 1 $ bug $end
$var parameter 4 % passkey $end
$var reg 1 & clk $end
$var reg 4 ' digits [3:0] $end
$var reg 1 ( reset $end
$var reg 1 ) submit $end
$upscope $end
$enddefinitions $end
$comment Show the parameter values. $end
$dumpall
b1010 %
$end
#0
$dumpvars
x)
x(
bx '
0&
x$
x#
x"
x!
$end
#5
1$
1&
#10
1$
0"
0#
1(
0&
#15
0$
1!
1&
#20
b10 '
0(
0&
#25
1)
1&
#30
b100 '
0)
0&
#35
1)
1&
#40
b1000 '
0)
0&
#45
1)
1&
#50
0)
0&
#55
1)
1&
#60
b10 '
0)
0&
#65
1)
1&
#70
b1 '
0)
0&
#75
1)
1&
#80
b1000 '
0)
0&
#85
1)
1&
#90
0)
0&
#95
1)
1&
#100
b10 '
0)
0&
#105
1)
1&
#110
0)
0&
#115
1)
1&
#120
0)
0&
#125
1)
1&
#130
0)
0&
#135
1)
1&
#140
b1 '
0)
0&
#145
1)
1&
#150
0)
0&
#155
1)
1&
#160
0)
0&
#165
1)
1&
#170
b100 '
0)
0&
#175
1)
1&
#180
0)
0&
#185
1)
1&
#190
0)
0&
#195
1)
1&
#200
b1 '
0)
0&
#205
1)
1&
#210
b1000 '
0)
0&
#215
1)
1&
#220
0)
0&
#225
1)
1&
#230
b1 '
0)
0&
#235
1)
1&
#240
0)
0&
#245
1)
1&
#250
b100 '
0)
0&
#255
1)
1&
#260
0)
0&
#265
1)
1&
#270
0)
0&
#275
1)
1&
#280
b10 '
0)
0&
#285
1)
1&
#290
b100 '
0)
0&
#295
1)
1&
#300
b1000 '
0)
0&
#305
1)
1&
#310
0)
0&
#315
1)
1&
#320
0)
0&
#325
1)
1&
#330
b10 '
0)
0&
#335
1)
1&
#340
b100 '
0)
0&
#345
1)
1&
#350
b10 '
0)
0&
#355
1)
1&
#360
b1 '
0)
0&
#365
1)
1&
#370
b100 '
0)
0&
#375
1)
1&
#380
0)
0&
#385
1)
1&
#390
b1000 '
0)
0&
#395
1)
1&
#400
0)
0&
#405
1)
1&
#410
0)
0&
#415
1)
1&
#420
b10 '
0)
0&
#425
1)
1&
#430
b100 '
0)
0&
#435
1)
1&
#440
b1000 '
0)
0&
#445
1)
1&
#450
b100 '
0)
0&
#455
1)
1&
#460
b10 '
0)
0&
#465
1)
1&
#470
b100 '
0)
0&
#475
1)
1&
#480
b10 '
0)
0&
#485
1)
1&
#490
0)
0&
#495
1)
1&
#500
b100 '
0)
0&
#505
1)
1&
#510
b1000 '
0)
0&
#515
1)
1&
#520
b1 '
0)
0&
#525
1)
1&
#530
0)
0&
#535
1)
1&
#540
b10 '
0)
0&
#545
1)
1&
#550
b100 '
0)
0&
#555
1)
1&
#560
b10 '
0)
0&
#565
1)
1&
#570
b100 '
0)
0&
#575
1)
1&
#580
b1 '
0)
0&
#585
1)
1&
#590
0)
0&
#595
1)
1&
#600
0)
0&
#605
1)
1&
#610
0)
0&
#615
1)
1&
#620
b100 '
0)
0&
#625
1)
1&
#630
b10 '
0)
0&
#635
1)
1&
#640
b1000 '
0)
0&
#645
1)
1&
#650
0)
0&
#655
1)
1&
#660
b1 '
0)
0&
#665
1)
1&
#670
b10 '
0)
0&
#675
1)
1&
#680
b1000 '
0)
0&
#685
1)
1&
#690
b10 '
0)
0&
#695
1)
1&
#700
b1000 '
0)
0&
#705
1)
1&
#710
b10 '
0)
0&
#715
1)
1&
#720
b1 '
0)
0&
#725
1)
1&
#730
0)
0&
#735
1)
1&
#740
b10 '
0)
0&
#745
1)
1&
#750
0)
0&
#755
1)
1&
#760
b1 '
0)
0&
#765
1)
1&
#770
0)
0&
#775
1)
1&
#780
0)
0&
#785
1)
1&
#790
b100 '
0)
0&
#795
1)
1&
#800
0)
0&
#805
1)
1&
#810
b1000 '
0)
0&
#815
1)
1&
#820
0)
0&
#825
1)
1&
#830
b1 '
0)
0&
#835
1)
1&
#840
b1000 '
0)
0&
#845
1)
1&
#850
b100 '
0)
0&
#855
1)
1&
#860
0)
0&
#865
1)
1&
#870
b1000 '
0)
0&
#875
1)
1&
#880
b1 '
0)
0&
#885
1)
1&
#890
b10 '
0)
0&
#895
1)
1&
#900
b100 '
0)
0&
#905
1)
1&
#910
b1 '
0)
0&
#915
1)
1&
#920
b1000 '
0)
0&
#925
1)
1&
#930
b10 '
0)
0&
#935
1)
1&
#940
0)
0&
#945
1)
1&
#950
b1000 '
0)
0&
#955
1)
1&
#960
b10 '
0)
0&
#965
1)
1&
#970
0)
0&
#975
1)
1&
#980
0)
0&
