DUT/HoldLED.v

module HoldLED #(parameter length= 250_000_000)(
	input clk,reset,
	output reg LED
	);
	
	reg [27:0] counter;
	
	always @(posedge clk)begin
		if(reset) begin
			counter<=0;
			LED <=1;
			

		end else if(counter<length)begin
			LED<=1;
			counter<= counter+1;
		end else begin
			LED<=0;
		end
		
	end
endmodule

DUT/PinCheck.v


module PinCheck #(parameter passkey = 4'b1010)(
    input [1:0] digit,
    input submit, reset, clk,
    output reg waiting, correct, incorrect,bug
);
    reg [2:0] state;
	reg update,verify;
	reg [2:0] dig_count;
	reg [7:0] password;
	reg firstDigit,secondDigit;
	reg right_wrong_in,right_wrong_out;
	reg [1:0] digit_stw;
	 
//Instantiate LED holding
	 HoldLED holdLED(
		.clk(clk),
		.reset(right_wrong_in),
		.LED(right_wrong_out)
	 );

 //state reset
		always @(posedge clk or posedge reset) begin
		  if(reset) begin
				state <= 0;
				correct<=0;
				incorrect<=0;
				bug<=0;
		  end
		end
		
//pinloading
		always @(posedge clk) begin
			if(reset) begin
				password <= 0;
				update<=0;
				dig_count<=0;
				verify<=0;
			end else if(firstDigit) begin
				password <= {password[6:0],digit_stw[1]};
				secondDigit<=1;
				firstDigit<=0;
			end else if(secondDigit) begin
				password <= {password[6:0],digit_stw[0]};
				secondDigit<=0;
				dig_count<= dig_count+1;
				update<=1;
			end else if (submit) begin
				firstDigit<=1;
				digit_stw<=digit;

			end
		end


//fsm logic
		always @(posedge clk or posedge reset) begin
		  case(state)
			0:begin//Default state
				waiting<=1;
				state <= update;
				verify<=0;
			end
			1:begin//Digit read state
				if(dig_count==4) begin//if all digits are read, move to next state
					update <= 2;
					waiting<=0;
					verify<=1;
				end else begin
					update<=0;
				end
				state <=update;		
			end
			2:begin//all digits have been read, 
			//TODO: verified timing logic with timing chart, need to decide what state 2 is.
			//Next step would be verification so i need to think about what verification logic will be and how it should relate to flags like waiting or other leds
			//waiting turns to 0 when update is assigned 2. Is this ideal? state only changes 2 cycles after update changes this should be considered.
				if(password == passkey) begin
					state <=3;
				end else begin
					state<=4;
				end
				verify<=0;
			end
			
			3:begin//correct password
				right_wrong_in<=1;
				correct<=1;
				state<=5;
				
			end
			
			4:begin//incorrect password
				right_wrong_in<=1;
				incorrect<=1;
				state<=5;
			end
			
			5:begin//Holding LED
				right_wrong_in<=0;
				if(right_wrong_out!=1) begin
					state<=0;
					correct<=0;
					incorrect<=0;
				end
					
			end
			
			default:begin
				bug<=1;
			end
		  endcase
		end


    
    

    

endmodule

DUT/Encoder.v
module priorityEncoder(
	input [3:0] in,
	output reg [1:0] out
	);
	
	
	always @(*)begin
      casez(in)
		4'b1???:out=3;
		4'b01??:out=2;
		4'b001?:out=1;
		4'b0001:out=0;
		default:begin
			out=1'bx;
			end
		endcase
	end
	
endmodule

DUT/DebitPin.v


module DebitPin #(parameter passkey = 4'b1010)(
    input digit_switches[3:0],
    input clk, reset, submit,
    output reg waiting, correct, incorrect,bug
);

    wire [1:0] digit;

    priorityEncoder priority_enc(
        .in(digit_switches),
        .out(digit)

    );

    PinCheck pinchk(
        .digit(digit),
        .submit(submit), .reset(reset), .clk(clk),
        .waiting(waiting), .correct(correct), .incorrect(incorrect),.bug(bug)
    );


endmodule

Testbench/tb_DebitPin/tb_top.sv
`ifndef passkey
    `define passkey  4'b1010
`endif


//Iverilog doesn't support constraints and random variable type :(
// class digit_item;

//     randc bit [3:0] digit;

//     constraint digit_lim {((digit == 4'b1000)||(digit == 4'b0100)||(digit == 4'b0010)||(digit == 4'b0001));}

//     function void print(string tag="");
//         $display("T=%0t [%s] digit=%0d",$time,digit);
//     endfunction
// endclass

module top();

    parameter passkey = `passkey;
   

    logic [3:0] digits;
    logic clk, reset, submit, waiting, correct, incorrect, bug;
    

    DebitPin #(passkey) debitpin(
        .digit_switches(digits),
        .clk(clk),
        .reset(reset),
        .submit(submit),
        .waiting(waiting),
        .correct(correct),
        .incorrect(incorrect),
        .bug(bug)
    );

    function automatic logic [1:0] encode (input logic [3:0] in);
        casez(in)
            4'b1???:encode = 2'd3;
            4'b01??:encode = 2'd2;
            4'b001?:encode = 2'd1;
            4'b0000:encode = 2'd0;
            default: encode = 2'bxx;
        endcase
    endfunction

    task DigitSubmission();//implement this testbench
        static bit [3:0] allowed_digits [0:3];
        logic [15:0] password;
        begin
            
            allowed_digits[0] = 4'b1000;
            allowed_digits[1] = 4'b0100;
            allowed_digits[2] = 4'b0010;
            allowed_digits[3] = 4'b0001;
            //for each digit
            repeat(24) begin
                password = 16'b0;

                repeat(4) begin
                    //randomize passkey selection
                    bit [3:0] digit;
                    digit = allowed_digits[$urandom_range(0, 3)];

                    //Track digits submitted
                    password = {password[11:0],digit};

                    //submit random digit
                    digits = digit;
                    @(posedge clk);
                        submit = 1;
                    @(negedge clk);
                        submit = 0;
                    //allow pincheck logic to update
                    repeat(2) begin
                        @(negedge clk);
                    end
                    //observe statemachine progression
                    $display("T=%0t,Sumbit = %0b,digits=%0b",$time,submit,digits);
                end
                assert(encode(password[15:12]) ==debitpin.pinchk.password[7:6]);
                assert(encode(password[11:8]) ==debitpin.pinchk.password[5:4]);
                assert(encode(password[7:4]) ==debitpin.pinchk.password[3:2]);
                assert(encode(password[3:0]) ==debitpin.pinchk.password[1:0]);
            end
        end

    endtask


    initial begin
        clk = 0;
        forever #5 clk = ~clk;
    end

    initial begin
        $dumpfile("dump.vcd");
        $dumpvars();
        $dumpvars(0,debitpin.pinchk);

        @(negedge clk);
            reset = 1;
        @(negedge clk);
            reset = 0;

        DigitSubmission();


        $finish();
    end

endmodule

//TODO: Correctly stores digit in top_level password shhift register- I think the submission timeline doesn't account for delay to the fsm as it doesnt update immediately in the pincheck so i need to dive into that.
//Verify clock timing on pincheck to observe if its behaving as desired based on stimulus

dump.vcd
$date
	Fri Aug 08 18:38:07 2025
$end
$version
	Icarus Verilog
$end
$timescale
	1s
$end
$scope module top $end
$var wire 1 ! waiting $end
$var wire 1 " incorrect $end
$var wire 1 # correct $end
$var wire 1 $ bug $end
$var parameter 4 % passkey $end
$var reg 1 & clk $end
$var reg 4 ' digits [3:0] $end
$var reg 1 ( reset $end
$var reg 1 ) submit $end
$scope function encode $end
$upscope $end
$scope module debitpin $end
$var wire 1 & clk $end
$var wire 4 * digit_switches [3:0] $end
$var wire 1 ( reset $end
$var wire 1 ) submit $end
$var wire 1 ! waiting $end
$var wire 1 " incorrect $end
$var wire 2 + digit [1:0] $end
$var wire 1 # correct $end
$var wire 1 $ bug $end
$var parameter 4 , passkey $end
$scope module pinchk $end
$var wire 1 & clk $end
$var wire 1 ( reset $end
$var wire 1 ) submit $end
$var wire 1 - right_wrong_out $end
$var wire 2 . digit [1:0] $end
$var parameter 4 / passkey $end
$var reg 1 $ bug $end
$var reg 1 # correct $end
$var reg 3 0 dig_count [2:0] $end
$var reg 2 1 digit_stw [1:0] $end
$var reg 1 2 firstDigit $end
$var reg 1 " incorrect $end
$var reg 8 3 password [7:0] $end
$var reg 1 4 right_wrong_in $end
$var reg 1 5 secondDigit $end
$var reg 3 6 state [2:0] $end
$var reg 1 7 update $end
$var reg 1 8 verify $end
$var reg 1 ! waiting $end
$scope module holdLED $end
$var wire 1 & clk $end
$var wire 1 4 reset $end
$var parameter 32 9 length $end
$var reg 1 - LED $end
$var reg 28 : counter [27:0] $end
$upscope $end
$upscope $end
$scope module priority_enc $end
$var wire 4 ; in [3:0] $end
$var reg 2 < out [1:0] $end
$upscope $end
$upscope $end
$scope task DigitSubmission $end
$var reg 16 = password [15:0] $end
$scope begin $unm_blk_29 $end
$var reg 4 > digit [3:0] $end
$upscope $end
$upscope $end
$upscope $end
$scope module top $end
$scope module debitpin $end
$scope module pinchk $end
$scope module holdLED $end
$upscope $end
$upscope $end
$upscope $end
$upscope $end
$enddefinitions $end
$comment Show the parameter values. $end
$dumpall
b1110111001101011001010000000 9
b1010 /
b1010 ,
b1010 %
$end
#0
$dumpvars
b0 >
bx =
bx <
bx ;
bx :
x8
x7
bx 6
x5
x4
bx 3
x2
bx 1
bx 0
bx .
x-
bx +
bx *
x)
x(
bx '
0&
x$
x#
x"
x!
$end
#5
1$
0-
1&
#10
1$
0"
0#
b0 6
1(
0&
#15
0$
b0 6
1!
08
b0 0
07
b0 3
1&
#20
b1 +
b1 .
b1 <
b10 '
b10 *
b10 ;
b10 >
b10 =
0(
0&
#25
b1 1
12
1)
1&
#30
0)
0&
#35
02
15
1&
#40
0&
#45
17
b1 0
05
b1 3
1&
#50
b10 +
b10 .
b10 <
b100 '
b100 *
b100 ;
b100100 =
b100 >
0&
#55
b1 6
b10 1
12
1)
1&
#60
0)
0&
#65
07
02
15
b11 3
1&
#70
0&
#75
b0 6
07
b10 0
05
b110 3
1&
#80
b11 +
b11 .
b11 <
b1000 '
b1000 *
b1000 ;
b1001001000 =
b1000 >
0&
#85
b11 1
12
1)
1&
#90
0)
0&
#95
02
15
b1101 3
1&
#100
0&
#105
17
b11 0
05
b11011 3
1&
#110
b10010010001000 =
0&
#115
b1 6
12
1)
1&
#120
0)
0&
#125
07
02
15
b110111 3
1&
#130
0&
#135
b0 6
07
b100 0
05
b1101111 3
1&
#140
b1 +
b1 .
b1 <
b10 '
b10 *
b10 ;
b10 >
b10 =
0&
#145
b1 1
12
1)
1&
#150
0)
0&
#155
02
15
b11011110 3
1&
#160
0&
#165
17
b101 0
05
b10111101 3
1&
#170
b1 '
b1 *
b1 ;
b100001 =
b1 >
0&
#175
b1 6
12
1)
1&
#180
0)
0&
#185
07
02
15
b1111010 3
1&
#190
0&
#195
b0 6
07
b110 0
05
b11110101 3
1&
#200
b11 +
b11 .
b11 <
b1000 '
b1000 *
b1000 ;
b1000011000 =
b1000 >
0&
#205
b11 1
12
1)
1&
#210
0)
0&
#215
02
15
b11101011 3
1&
#220
0&
#225
17
b111 0
05
b11010111 3
1&
#230
b10000110001000 =
0&
#235
b1 6
12
1)
1&
#240
0)
0&
#245
07
02
15
b10101111 3
1&
#250
0&
#255
b0 6
07
b0 0
05
b1011111 3
1&
#260
b1 +
b1 .
b1 <
b10 '
b10 *
b10 ;
b10 >
b10 =
0&
#265
b1 1
12
1)
1&
#270
0)
0&
#275
02
15
b10111110 3
1&
#280
0&
#285
17
b1 0
05
b1111101 3
1&
#290
b100010 =
0&
#295
b1 6
12
1)
1&
#300
0)
0&
#305
07
02
15
b11111010 3
1&
#310
0&
#315
b0 6
07
b10 0
05
b11110101 3
1&
#320
b1000100010 =
0&
#325
12
1)
1&
#330
0)
0&
#335
02
15
b11101010 3
1&
#340
0&
#345
17
b11 0
05
b11010101 3
1&
#350
b10001000100010 =
0&
#355
b1 6
12
1)
1&
#360
0)
0&
#365
07
02
15
b10101010 3
1&
#370
0&
#375
b0 6
07
b100 0
05
b1010101 3
1&
#380
b1 '
b1 *
b1 ;
b1 >
b1 =
0&
#385
12
1)
1&
#390
0)
0&
#395
02
15
b10101010 3
1&
#400
0&
#405
17
b101 0
05
b1010101 3
1&
#410
b10001 =
0&
#415
b1 6
12
1)
1&
#420
0)
0&
#425
07
02
15
b10101010 3
1&
#430
0&
#435
b0 6
07
b110 0
05
b1010101 3
1&
#440
b100010001 =
0&
#445
12
1)
1&
#450
0)
0&
#455
02
15
b10101010 3
1&
#460
0&
#465
17
b111 0
05
b1010101 3
1&
#470
b10 +
b10 .
b10 <
b100 '
b100 *
b100 ;
b1000100010100 =
b100 >
0&
#475
b1 6
b10 1
12
1)
1&
#480
0)
0&
#485
07
02
15
b10101011 3
1&
#490
0&
#495
b0 6
07
b0 0
05
b1010110 3
1&
#500
b100 =
0&
#505
12
1)
1&
#510
0)
0&
#515
02
15
b10101101 3
1&
#520
0&
#525
17
b1 0
05
b1011010 3
1&
#530
b1000100 =
0&
#535
b1 6
12
1)
1&
#540
0)
0&
#545
07
02
15
b10110101 3
1&
#550
0&
#555
b0 6
07
b10 0
05
b1101010 3
1&
#560
b1 +
b1 .
b1 <
b1 '
b1 *
b1 ;
b10001000001 =
b1 >
0&
#565
b1 1
12
1)
1&
#570
0)
0&
#575
02
15
b11010100 3
1&
#580
0&
#585
17
b11 0
05
b10101001 3
1&
#590
b11 +
b11 .
b11 <
b1000 '
b1000 *
b1000 ;
b100010000011000 =
b1000 >
0&
#595
b1 6
b11 1
12
1)
1&
#600
0)
0&
#605
07
02
15
b1010011 3
1&
#610
0&
#615
b0 6
07
b100 0
05
b10100111 3
1&
#620
b1000 =
0&
#625
12
1)
1&
#630
0)
0&
#635
02
15
b1001111 3
1&
#640
0&
#645
17
b101 0
05
b10011111 3
1&
#650
b1 +
b1 .
b1 <
b1 '
b1 *
b1 ;
b10000001 =
b1 >
0&
#655
b1 6
b1 1
12
1)
1&
#660
0)
0&
#665
07
02
15
b111110 3
1&
#670
0&
#675
b0 6
07
b110 0
05
b1111101 3
1&
#680
b100000010001 =
0&
#685
12
1)
1&
#690
0)
0&
#695
02
15
b11111010 3
1&
#700
0&
#705
17
b111 0
05
b11110101 3
1&
#710
b10 +
b10 .
b10 <
b100 '
b100 *
b100 ;
b1000000100010100 =
b100 >
0&
#715
b1 6
b10 1
12
1)
1&
#720
0)
0&
#725
07
02
15
b11101011 3
1&
#730
0&
#735
b0 6
07
b0 0
05
b11010110 3
1&
#740
b100 =
0&
#745
12
1)
1&
#750
0)
0&
#755
02
15
b10101101 3
1&
#760
0&
#765
17
b1 0
05
b1011010 3
1&
#770
b1000100 =
0&
#775
b1 6
12
1)
1&
#780
0)
0&
#785
07
02
15
b10110101 3
1&
#790
0&
#795
b0 6
07
b10 0
05
b1101010 3
1&
#800
b1 +
b1 .
b1 <
b10 '
b10 *
b10 ;
b10001000010 =
b10 >
0&
#805
b1 1
12
1)
1&
#810
0)
0&
#815
02
15
b11010100 3
1&
#820
0&
#825
17
b11 0
05
b10101001 3
1&
#830
b10 +
b10 .
b10 <
b100 '
b100 *
b100 ;
b100010000100100 =
b100 >
0&
#835
b1 6
b10 1
12
1)
1&
#840
0)
0&
#845
07
02
15
b1010011 3
1&
#850
0&
#855
b0 6
07
b100 0
05
b10100110 3
1&
#860
b11 +
b11 .
b11 <
b1000 '
b1000 *
b1000 ;
b1000 >
b1000 =
0&
#865
b11 1
12
1)
1&
#870
0)
0&
#875
02
15
b1001101 3
1&
#880
0&
#885
17
b101 0
05
b10011011 3
1&
#890
b10001000 =
0&
#895
b1 6
12
1)
1&
#900
0)
0&
#905
07
02
15
b110111 3
1&
#910
0&
#915
b0 6
07
b110 0
05
b1101111 3
1&
#920
b100010001000 =
0&
#925
12
1)
1&
#930
0)
0&
#935
02
15
b11011111 3
1&
#940
0&
#945
17
b111 0
05
b10111111 3
1&
#950
b1 +
b1 .
b1 <
b10 '
b10 *
b10 ;
b1000100010000010 =
b10 >
0&
#955
b1 6
b1 1
12
1)
1&
#960
0)
0&
#965
07
02
15
b1111110 3
1&
#970
0&
#975
b0 6
07
b0 0
05
b11111101 3
1&
#980
b10 +
b10 .
b10 <
b100 '
b100 *
b100 ;
b100 >
b100 =
0&
#985
b10 1
12
1)
1&
#990
0)
0&
#995
02
15
b11111011 3
1&
#1000
0&
#1005
17
b1 0
05
b11110110 3
1&
#1010
b1 +
b1 .
b1 <
b10 '
b10 *
b10 ;
b1000010 =
b10 >
0&
#1015
b1 6
b1 1
12
1)
1&
#1020
0)
0&
#1025
07
02
15
b11101100 3
1&
#1030
0&
#1035
b0 6
07
b10 0
05
b11011001 3
1&
#1040
b1 '
b1 *
b1 ;
b10000100001 =
b1 >
0&
#1045
12
1)
1&
#1050
0)
0&
#1055
02
15
b10110010 3
1&
#1060
0&
#1065
17
b11 0
05
b1100101 3
1&
#1070
b10 +
b10 .
b10 <
b100 '
b100 *
b100 ;
b100001000010100 =
b100 >
0&
#1075
b1 6
b10 1
12
1)
1&
#1080
0)
0&
#1085
07
02
15
b11001011 3
1&
#1090
0&
#1095
b0 6
07
b100 0
05
b10010110 3
1&
#1100
b100 =
0&
#1105
12
1)
1&
#1110
0)
0&
#1115
02
15
b101101 3
1&
#1120
0&
#1125
17
b101 0
05
b1011010 3
1&
#1130
b11 +
b11 .
b11 <
b1000 '
b1000 *
b1000 ;
b1001000 =
b1000 >
0&
#1135
b1 6
b11 1
12
1)
1&
#1140
0)
0&
#1145
07
02
15
b10110101 3
1&
#1150
0&
#1155
b0 6
07
b110 0
05
b1101011 3
1&
#1160
b10010001000 =
0&
#1165
12
1)
1&
#1170
0)
0&
#1175
02
15
b11010111 3
1&
#1180
0&
#1185
17
b111 0
05
b10101111 3
1&
#1190
b100100010001000 =
0&
#1195
b1 6
12
1)
1&
#1200
0)
0&
#1205
07
02
15
b1011111 3
1&
#1210
0&
#1215
b0 6
07
b0 0
05
b10111111 3
1&
#1220
b1 +
b1 .
b1 <
b10 '
b10 *
b10 ;
b10 >
b10 =
0&
#1225
b1 1
12
1)
1&
#1230
0)
0&
#1235
02
15
b1111110 3
1&
#1240
0&
#1245
17
b1 0
05
b11111101 3
1&
#1250
b10 +
b10 .
b10 <
b100 '
b100 *
b100 ;
b100100 =
b100 >
0&
#1255
b1 6
b10 1
12
1)
1&
#1260
0)
0&
#1265
07
02
15
b11111011 3
1&
#1270
0&
#1275
b0 6
07
b10 0
05
b11110110 3
1&
#1280
b11 +
b11 .
b11 <
b1000 '
b1000 *
b1000 ;
b1001001000 =
b1000 >
0&
#1285
b11 1
12
1)
1&
#1290
0)
0&
#1295
02
15
b11101101 3
1&
#1300
0&
#1305
17
b11 0
05
b11011011 3
1&
#1310
b10 +
b10 .
b10 <
b100 '
b100 *
b100 ;
b10010010000100 =
b100 >
0&
#1315
b1 6
b10 1
12
1)
1&
#1320
0)
0&
#1325
07
02
15
b10110111 3
1&
#1330
0&
#1335
b0 6
07
b100 0
05
b1101110 3
1&
#1340
b1 +
b1 .
b1 <
b10 '
b10 *
b10 ;
b10 >
b10 =
0&
#1345
b1 1
12
1)
1&
#1350
0)
0&
#1355
02
15
b11011100 3
1&
#1360
0&
#1365
17
b101 0
05
b10111001 3
1&
#1370
b10 +
b10 .
b10 <
b100 '
b100 *
b100 ;
b100100 =
b100 >
0&
#1375
b1 6
b10 1
12
1)
1&
#1380
0)
0&
#1385
07
02
15
b1110011 3
1&
#1390
0&
#1395
b0 6
07
b110 0
05
b11100110 3
1&
#1400
b1 +
b1 .
b1 <
b10 '
b10 *
b10 ;
b1001000010 =
b10 >
0&
#1405
b1 1
12
1)
1&
#1410
0)
0&
#1415
02
15
b11001100 3
1&
#1420
0&
#1425
17
b111 0
05
b10011001 3
1&
#1430
b10010000100010 =
0&
#1435
b1 6
12
1)
1&
#1440
0)
0&
#1445
07
02
15
b110010 3
1&
#1450
0&
#1455
b0 6
07
b0 0
05
b1100101 3
1&
#1460
b10 +
b10 .
b10 <
b100 '
b100 *
b100 ;
b100 >
b100 =
0&
#1465
b10 1
12
1)
1&
#1470
0)
0&
#1475
02
15
b11001011 3
1&
#1480
0&
#1485
17
b1 0
05
b10010110 3
1&
#1490
b11 +
b11 .
b11 <
b1000 '
b1000 *
b1000 ;
b1001000 =
b1000 >
0&
#1495
b1 6
b11 1
12
1)
1&
#1500
0)
0&
#1505
07
02
15
b101101 3
1&
#1510
0&
#1515
b0 6
07
b10 0
05
b1011011 3
1&
#1520
b1 +
b1 .
b1 <
b1 '
b1 *
b1 ;
b10010000001 =
b1 >
0&
#1525
b1 1
12
1)
1&
#1530
0)
0&
#1535
02
15
b10110110 3
1&
#1540
0&
#1545
17
b11 0
05
b1101101 3
1&
#1550
b100100000010001 =
0&
#1555
b1 6
12
1)
1&
#1560
0)
0&
#1565
07
02
15
b11011010 3
1&
#1570
0&
#1575
b0 6
07
b100 0
05
b10110101 3
1&
#1580
b10 '
b10 *
b10 ;
b10 >
b10 =
0&
#1585
12
1)
1&
#1590
0)
0&
#1595
02
15
b1101010 3
1&
#1600
0&
#1605
17
b101 0
05
b11010101 3
1&
#1610
b10 +
b10 .
b10 <
b100 '
b100 *
b100 ;
b100100 =
b100 >
0&
#1615
b1 6
b10 1
12
1)
1&
#1620
0)
0&
#1625
07
02
15
b10101011 3
1&
#1630
0&
#1635
b0 6
07
b110 0
05
b1010110 3
1&
#1640
b1 +
b1 .
b1 <
b10 '
b10 *
b10 ;
b1001000010 =
b10 >
0&
#1645
b1 1
12
1)
1&
#1650
0)
0&
#1655
02
15
b10101100 3
1&
#1660
0&
#1665
17
b111 0
05
b1011001 3
1&
#1670
b10 +
b10 .
b10 <
b100 '
b100 *
b100 ;
b10010000100100 =
b100 >
0&
#1675
b1 6
b10 1
12
1)
1&
#1680
0)
0&
#1685
07
02
15
b10110011 3
1&
#1690
0&
#1695
b0 6
07
b0 0
05
b1100110 3
1&
#1700
b1 +
b1 .
b1 <
b1 '
b1 *
b1 ;
b1 >
b1 =
0&
#1705
b1 1
12
1)
1&
#1710
0)
0&
#1715
02
15
b11001100 3
1&
#1720
0&
#1725
17
b1 0
05
b10011001 3
1&
#1730
b10001 =
0&
#1735
b1 6
12
1)
1&
#1740
0)
0&
#1745
07
02
15
b110010 3
1&
#1750
0&
#1755
b0 6
07
b10 0
05
b1100101 3
1&
#1760
b100010001 =
0&
#1765
12
1)
1&
#1770
0)
0&
#1775
02
15
b11001010 3
1&
#1780
0&
#1785
17
b11 0
05
b10010101 3
1&
#1790
b1000100010001 =
0&
#1795
b1 6
12
1)
1&
#1800
0)
0&
#1805
07
02
15
b101010 3
1&
#1810
0&
#1815
b0 6
07
b100 0
05
b1010101 3
1&
#1820
b10 +
b10 .
b10 <
b100 '
b100 *
b100 ;
b100 >
b100 =
0&
#1825
b10 1
12
1)
1&
#1830
0)
0&
#1835
02
15
b10101011 3
1&
#1840
0&
#1845
17
b101 0
05
b1010110 3
1&
#1850
b1 +
b1 .
b1 <
b10 '
b10 *
b10 ;
b1000010 =
b10 >
0&
#1855
b1 6
b1 1
12
1)
1&
#1860
0)
0&
#1865
07
02
15
b10101100 3
1&
#1870
0&
#1875
b0 6
07
b110 0
05
b1011001 3
1&
#1880
b11 +
b11 .
b11 <
b1000 '
b1000 *
b1000 ;
b10000101000 =
b1000 >
0&
#1885
b11 1
12
1)
1&
#1890
0)
0&
#1895
02
15
b10110011 3
1&
#1900
0&
#1905
17
b111 0
05
b1100111 3
1&
#1910
b100001010001000 =
0&
#1915
b1 6
12
1)
1&
#1920
0)
0&
#1925
07
02
15
b11001111 3
1&
#1930
0&
#1935
b0 6
07
b0 0
05
b10011111 3
1&
#1940
b1 +
b1 .
b1 <
b1 '
b1 *
b1 ;
b1 >
b1 =
0&
#1945
b1 1
12
1)
1&
#1950
0)
0&
#1955
02
15
b111110 3
1&
#1960
0&
#1965
17
b1 0
05
b1111101 3
1&
#1970
b10 '
b10 *
b10 ;
b10010 =
b10 >
0&
#1975
b1 6
12
1)
1&
#1980
0)
0&
#1985
07
02
15
b11111010 3
1&
#1990
0&
#1995
b0 6
07
b10 0
05
b11110101 3
1&
#2000
b11 +
b11 .
b11 <
b1000 '
b1000 *
b1000 ;
b100101000 =
b1000 >
0&
#2005
b11 1
12
1)
1&
#2010
0)
0&
#2015
02
15
b11101011 3
1&
#2020
0&
#2025
17
b11 0
05
b11010111 3
1&
#2030
b1 +
b1 .
b1 <
b10 '
b10 *
b10 ;
b1001010000010 =
b10 >
0&
#2035
b1 6
b1 1
12
1)
1&
#2040
0)
0&
#2045
07
02
15
b10101110 3
1&
#2050
0&
#2055
b0 6
07
b100 0
05
b1011101 3
1&
#2060
b11 +
b11 .
b11 <
b1000 '
b1000 *
b1000 ;
b1000 >
b1000 =
0&
#2065
b11 1
12
1)
1&
#2070
0)
0&
#2075
02
15
b10111011 3
1&
#2080
0&
#2085
17
b101 0
05
b1110111 3
1&
#2090
b1 +
b1 .
b1 <
b10 '
b10 *
b10 ;
b10000010 =
b10 >
0&
#2095
b1 6
b1 1
12
1)
1&
#2100
0)
0&
#2105
07
02
15
b11101110 3
1&
#2110
0&
#2115
b0 6
07
b110 0
05
b11011101 3
1&
#2120
b1 '
b1 *
b1 ;
b100000100001 =
b1 >
0&
#2125
12
1)
1&
#2130
0)
0&
#2135
02
15
b10111010 3
1&
#2140
0&
#2145
17
b111 0
05
b1110101 3
1&
#2150
b1000001000010001 =
0&
#2155
b1 6
12
1)
1&
#2160
0)
0&
#2165
07
02
15
b11101010 3
1&
#2170
0&
#2175
b0 6
07
b0 0
05
b11010101 3
1&
#2180
b10 '
b10 *
b10 ;
b10 >
b10 =
0&
#2185
12
1)
1&
#2190
0)
0&
#2195
02
15
b10101010 3
1&
#2200
0&
#2205
17
b1 0
05
b1010101 3
1&
#2210
b100010 =
0&
#2215
b1 6
12
1)
1&
#2220
0)
0&
#2225
07
02
15
b10101010 3
1&
#2230
0&
#2235
b0 6
07
b10 0
05
b1010101 3
1&
#2240
b1 '
b1 *
b1 ;
b1000100001 =
b1 >
0&
#2245
12
1)
1&
#2250
0)
0&
#2255
02
15
b10101010 3
1&
#2260
0&
#2265
17
b11 0
05
b1010101 3
1&
#2270
b10001000010001 =
0&
#2275
b1 6
12
1)
1&
#2280
0)
0&
#2285
07
02
15
b10101010 3
1&
#2290
0&
#2295
b0 6
07
b100 0
05
b1010101 3
1&
#2300
b1 =
0&
#2305
12
1)
1&
#2310
0)
0&
#2315
02
15
b10101010 3
1&
#2320
0&
#2325
17
b101 0
05
b1010101 3
1&
#2330
b10 +
b10 .
b10 <
b100 '
b100 *
b100 ;
b10100 =
b100 >
0&
#2335
b1 6
b10 1
12
1)
1&
#2340
0)
0&
#2345
07
02
15
b10101011 3
1&
#2350
0&
#2355
b0 6
07
b110 0
05
b1010110 3
1&
#2360
b101000100 =
0&
#2365
12
1)
1&
#2370
0)
0&
#2375
02
15
b10101101 3
1&
#2380
0&
#2385
17
b111 0
05
b1011010 3
1&
#2390
b11 +
b11 .
b11 <
b1000 '
b1000 *
b1000 ;
b1010001001000 =
b1000 >
0&
#2395
b1 6
b11 1
12
1)
1&
#2400
0)
0&
#2405
07
02
15
b10110101 3
1&
#2410
0&
#2415
b0 6
07
b0 0
05
b1101011 3
1&
#2420
b1000 =
0&
#2425
12
1)
1&
#2430
0)
0&
#2435
02
15
b11010111 3
1&
#2440
0&
#2445
17
b1 0
05
b10101111 3
1&
#2450
b1 +
b1 .
b1 <
b1 '
b1 *
b1 ;
b10000001 =
b1 >
0&
#2455
b1 6
b1 1
12
1)
1&
#2460
0)
0&
#2465
07
02
15
b1011110 3
1&
#2470
0&
#2475
b0 6
07
b10 0
05
b10111101 3
1&
#2480
b11 +
b11 .
b11 <
b1000 '
b1000 *
b1000 ;
b100000011000 =
b1000 >
0&
#2485
b11 1
12
1)
1&
#2490
0)
0&
#2495
02
15
b1111011 3
1&
#2500
0&
#2505
17
b11 0
05
b11110111 3
1&
#2510
b10 +
b10 .
b10 <
b100 '
b100 *
b100 ;
b1000000110000100 =
b100 >
0&
#2515
b1 6
b10 1
12
1)
1&
#2520
0)
0&
#2525
07
02
15
b11101111 3
1&
#2530
0&
#2535
b0 6
07
b100 0
05
b11011110 3
1&
#2540
b100 =
0&
#2545
12
1)
1&
#2550
0)
0&
#2555
02
15
b10111101 3
1&
#2560
0&
#2565
17
b101 0
05
b1111010 3
1&
#2570
b11 +
b11 .
b11 <
b1000 '
b1000 *
b1000 ;
b1001000 =
b1000 >
0&
#2575
b1 6
b11 1
12
1)
1&
#2580
0)
0&
#2585
07
02
15
b11110101 3
1&
#2590
0&
#2595
b0 6
07
b110 0
05
b11101011 3
1&
#2600
b1 +
b1 .
b1 <
b1 '
b1 *
b1 ;
b10010000001 =
b1 >
0&
#2605
b1 1
12
1)
1&
#2610
0)
0&
#2615
02
15
b11010110 3
1&
#2620
0&
#2625
17
b111 0
05
b10101101 3
1&
#2630
b10 '
b10 *
b10 ;
b100100000010010 =
b10 >
0&
#2635
b1 6
12
1)
1&
#2640
0)
0&
#2645
07
02
15
b1011010 3
1&
#2650
0&
#2655
b0 6
07
b0 0
05
b10110101 3
1&
#2660
b10 +
b10 .
b10 <
b100 '
b100 *
b100 ;
b100 >
b100 =
0&
#2665
b10 1
12
1)
1&
#2670
0)
0&
#2675
02
15
b1101011 3
1&
#2680
0&
#2685
17
b1 0
05
b11010110 3
1&
#2690
b1 +
b1 .
b1 <
b1 '
b1 *
b1 ;
b1000001 =
b1 >
0&
#2695
b1 6
b1 1
12
1)
1&
#2700
0)
0&
#2705
07
02
15
b10101100 3
1&
#2710
0&
#2715
b0 6
07
b10 0
05
b1011001 3
1&
#2720
b11 +
b11 .
b11 <
b1000 '
b1000 *
b1000 ;
b10000011000 =
b1000 >
0&
#2725
b11 1
12
1)
1&
#2730
0)
0&
#2735
02
15
b10110011 3
1&
#2740
0&
#2745
17
b11 0
05
b1100111 3
1&
#2750
b1 +
b1 .
b1 <
b10 '
b10 *
b10 ;
b100000110000010 =
b10 >
0&
#2755
b1 6
b1 1
12
1)
1&
#2760
0)
0&
#2765
07
02
15
b11001110 3
1&
#2770
0&
#2775
b0 6
07
b100 0
05
b10011101 3
1&
#2780
b10 =
0&
#2785
12
1)
1&
#2790
0)
0&
#2795
02
15
b111010 3
1&
#2800
0&
#2805
17
b101 0
05
b1110101 3
1&
#2810
b11 +
b11 .
b11 <
b1000 '
b1000 *
b1000 ;
b101000 =
b1000 >
0&
#2815
b1 6
b11 1
12
1)
1&
#2820
0)
0&
#2825
07
02
15
b11101011 3
1&
#2830
0&
#2835
b0 6
07
b110 0
05
b11010111 3
1&
#2840
b1 +
b1 .
b1 <
b10 '
b10 *
b10 ;
b1010000010 =
b10 >
0&
#2845
b1 1
12
1)
1&
#2850
0)
0&
#2855
02
15
b10101110 3
1&
#2860
0&
#2865
17
b111 0
05
b1011101 3
1&
#2870
b10100000100010 =
0&
