DUT/HoldLED.v

module HoldLED #(parameter length= 250_000_000)(
	input clk,reset,
	output reg LED
	);
	
	reg [27:0] counter;
	
	always @(posedge clk)begin
		if(reset) begin
			counter<=0;
			LED <=1;
			

		end else if(counter<length)begin
			LED<=1;
			counter<= counter+1;
		end else begin
			LED<=0;
		end
		
	end
endmodule

DUT/PinCheck.v


module PinCheck #(parameter passkey = 8'b10100101)(
    input [1:0] digit,
    input submit, reset, clk,
    output reg waiting, correct, incorrect,bug
);
   reg [2:0] state;
	reg update;
	reg verify;
	reg [2:0] dig_count;
	reg [7:0] password;
	reg firstDigit,secondDigit;
	reg right_wrong_in;
	wire right_wrong_out;
	reg [1:0] digit_stw;
	 
//Instantiate LED holding
	 HoldLED holdLED(
		.clk(clk),
		.reset(right_wrong_in),
		.LED(right_wrong_out)
	 );

 //state reset
		always @(posedge clk or posedge reset) begin
		  
		end
		
//pinloading
		always @(posedge clk) begin
			if(reset) begin
				password <= 0;
				dig_count<=0;
				verify<=0;
			end else if(firstDigit) begin
				password <= {password[6:0],digit_stw[1]};
				secondDigit<=1;
				firstDigit<=0;
			end else if(secondDigit ) begin
				password <= {password[6:0],digit_stw[0]};
				secondDigit<=0;
				dig_count<= dig_count+1;
			end else if (submit && (state == 0 || state  == 1)) begin
				firstDigit<=1;
				digit_stw<=digit;
				if (dig_count == 4) dig_count <=0;

			end
		end


//fsm logic
		always @(posedge clk) begin
			if(reset) begin
				state <= 0;
				correct<=0;
				incorrect<=0;
				bug<=0;
		  end else begin
			  case(state)
				0:begin//Default state
					if (submit) state<=1;
					waiting<=1;
					verify<=0;
					
				end
				1:begin//Digit read state
					if(dig_count==4) begin//if all digits are read, move to next state
						state <= 2;
						waiting<=0;
						verify<=1;
					end 
				end
				2:begin//all digits have been read, 
				//TODO: verified timing logic with timing chart, need to decide what state 2 is.
				//Next step would be verification so i need to think about what verification logic will be and how it should relate to flags like waiting or other leds
				//waiting turns to 0 when update is assigned 2. Is this ideal? state only changes 2 cycles after update changes this should be considered.
					if(password == passkey) begin
						state <=3;
					end else begin
						state<=4;
					end
					verify<=0;
				end
				
				3:begin//correct password
					right_wrong_in<=1;
					correct<=1;
					state<=5;
					
				end
				
				4:begin//incorrect password
					right_wrong_in<=1;
					incorrect<=1;
					state<=5;
				end
				
				5:begin//Activate LED
					right_wrong_in<=0;
					state<=6;
				end

				6: begin//Hold LED
					if(right_wrong_out!=1) begin
						state<=0;
						correct<=0;
						incorrect<=0;
					end
				end
				
				default:begin
					bug<=1;
				end
			  endcase
			  end
		end


    
    

    

endmodule

DUT/Encoder.v
module priorityEncoder(
	input [3:0] in,
	output reg [1:0] out
	);
	
	
	always @(*)begin
      casez(in)
		4'b1???:out=3;
		4'b01??:out=2;
		4'b001?:out=1;
		4'b0001:out=0;
		default:begin
			out=1'bx;
			end
		endcase
	end
	
endmodule

DUT/DebitPin.v


module DebitPin #(parameter passkey = 4'b1010)(
    input digit_switches[3:0],
    input clk, reset, submit,
    output reg waiting, correct, incorrect,bug
);

    wire [1:0] digit;

    priorityEncoder priority_enc(
        .in(digit_switches),
        .out(digit)

    );

    PinCheck pinchk(
        .digit(digit),
        .submit(submit), .reset(reset), .clk(clk),
        .waiting(waiting), .correct(correct), .incorrect(incorrect),.bug(bug)
    );


endmodule

Testbench/tb_DebitPin/tb_top.sv
`ifndef passkey
    `define passkey  4'b1010
`endif


//Iverilog doesn't support constraints and random variable type :(
// class digit_item;

//     randc bit [3:0] digit;

//     constraint digit_lim {((digit == 4'b1000)||(digit == 4'b0100)||(digit == 4'b0010)||(digit == 4'b0001));}

//     function void print(string tag="");
//         $display("T=%0t [%s] digit=%0d",$time,digit);
//     endfunction
// endclass

module top();

    parameter passkey = `passkey;
   

    logic [3:0] digits;
    logic clk, reset, submit, waiting, correct, incorrect, bug;
    

    DebitPin #(passkey) debitpin(
        .digit_switches(digits),
        .clk(clk),
        .reset(reset),
        .submit(submit),
        .waiting(waiting),
        .correct(correct),
        .incorrect(incorrect),
        .bug(bug)
    );

    function automatic logic [1:0] encode (input logic [3:0] in);
        casez(in)
            4'b1???:encode = 2'd3;
            4'b01??:encode = 2'd2;
            4'b001?:encode = 2'd1;
            4'b0001:encode = 2'd0;
            default: encode = 2'bxx;
        endcase
    endfunction

    task DigitSubmission();//implement this testbench
        static bit [3:0] allowed_digits [0:3];
        logic [15:0] password;
        begin
            
            allowed_digits[0] = 4'b1000;
            allowed_digits[1] = 4'b0100;
            allowed_digits[2] = 4'b0010;
            allowed_digits[3] = 4'b0001;
            //for each digit
            repeat(24) @(posedge clk) begin
                password = 16'b0;

                repeat(4) begin
                    //randomize passkey selection
                    bit [3:0] digit;
                    digit = allowed_digits[$urandom_range(0, 3)];

                    //Track digits submitted
                    password = {password[11:0],digit};

                    //submit random digit
                    digits = digit;
                    @(posedge clk);
                        submit = 1;
                    @(negedge clk);
                        submit = 0;
                    //allow pincheck logic to update
                    repeat(2) begin
                        @(negedge clk);
                    end
                    //observe statemachine progression
                    $display("T=%0t,passowrd = %0b,encode=%0b",$time,password[15:12],encode(password[15:12]));
                    $display("passowrd = %0b,encode=%0b",password[11:8],encode(password[11:8]));
                    $display("passowrd = %0b,encode=%0b",password[7:4],encode(password[7:4]));
                    $display("passowrd = %0b,encode=%0b",password[3:0],encode(password[3:0]));
                end
                assert(encode(password[15:12]) ==debitpin.pinchk.password[7:6]);
                assert(encode(password[11:8]) ==debitpin.pinchk.password[5:4]);
                assert(encode(password[7:4]) ==debitpin.pinchk.password[3:2]);
                assert(encode(password[3:0]) ==debitpin.pinchk.password[1:0]);
            end
        end

    endtask



    initial begin
        clk = 0;
        forever #5 clk = ~clk;
    end

    initial begin
        $dumpfile("dump.vcd");
        $dumpvars();
        $dumpvars(0,debitpin.pinchk);

        @(negedge clk);
            reset = 1;
        @(negedge clk);
            reset = 0;

        DigitSubmission();


        $finish();
    end

endmodule

//TODO: "Seems to be error with assertions and the logic seems correct, need to check how encode function acts on password and if assertions are wrong- consider adding print statements"

dump.vcd
$date
	Sat Aug 09 14:27:49 2025
$end
$version
	Icarus Verilog
$end
$timescale
	1s
$end
$scope module top $end
$var wire 1 ! waiting $end
$var wire 1 " incorrect $end
$var wire 1 # correct $end
$var wire 1 $ bug $end
$var parameter 4 % passkey $end
$var reg 1 & clk $end
$var reg 4 ' digits [3:0] $end
$var reg 1 ( reset $end
$var reg 1 ) submit $end
$scope function encode $end
$upscope $end
$scope module debitpin $end
$var wire 1 & clk $end
$var wire 4 * digit_switches [3:0] $end
$var wire 1 ( reset $end
$var wire 1 ) submit $end
$var wire 1 ! waiting $end
$var wire 1 " incorrect $end
$var wire 2 + digit [1:0] $end
$var wire 1 # correct $end
$var wire 1 $ bug $end
$var parameter 4 , passkey $end
$scope module pinchk $end
$var wire 1 & clk $end
$var wire 1 ( reset $end
$var wire 1 ) submit $end
$var wire 1 - right_wrong_out $end
$var wire 2 . digit [1:0] $end
$var parameter 4 / passkey $end
$var reg 1 $ bug $end
$var reg 1 # correct $end
$var reg 3 0 dig_count [2:0] $end
$var reg 2 1 digit_stw [1:0] $end
$var reg 1 2 firstDigit $end
$var reg 1 " incorrect $end
$var reg 8 3 password [7:0] $end
$var reg 1 4 right_wrong_in $end
$var reg 1 5 secondDigit $end
$var reg 3 6 state [2:0] $end
$var reg 1 7 update $end
$var reg 1 8 verify $end
$var reg 1 ! waiting $end
$scope module holdLED $end
$var wire 1 & clk $end
$var wire 1 4 reset $end
$var parameter 32 9 length $end
$var reg 1 - LED $end
$var reg 28 : counter [27:0] $end
$upscope $end
$upscope $end
$scope module priority_enc $end
$var wire 4 ; in [3:0] $end
$var reg 2 < out [1:0] $end
$upscope $end
$upscope $end
$scope task DigitSubmission $end
$var reg 16 = password [15:0] $end
$scope begin $unm_blk_29 $end
$var reg 4 > digit [3:0] $end
$upscope $end
$upscope $end
$upscope $end
$scope module top $end
$scope module debitpin $end
$scope module pinchk $end
$scope module holdLED $end
$upscope $end
$upscope $end
$upscope $end
$upscope $end
$enddefinitions $end
$comment Show the parameter values. $end
$dumpall
b1110111001101011001010000000 9
b1010 /
b1010 ,
b1010 %
$end
#0
$dumpvars
b0 >
bx =
bx <
bx ;
bx :
x8
x7
bx 6
x5
x4
bx 3
x2
bx 1
bx 0
bx .
x-
bx +
bx *
x)
x(
bx '
0&
x$
x#
x"
x!
$end
#5
1$
0-
1&
#10
1$
0"
0#
b0 6
1(
0&
#15
0$
b0 6
1!
08
b0 0
07
b0 3
1&
#20
0(
0&
#25
b1 +
b1 .
b1 <
b10 '
b10 *
b10 ;
b10 >
b10 =
1&
#30
0&
#35
b1 1
12
1)
1&
#40
0)
0&
#45
02
15
1&
#50
0&
#55
17
b1 0
05
b1 3
1&
#60
b10 +
b10 .
b10 <
b100 '
b100 *
b100 ;
b100100 =
b100 >
0&
#65
b1 6
b10 1
12
1)
1&
#70
0)
0&
#75
07
02
15
b11 3
1&
#80
0&
#85
b0 6
07
b10 0
05
b110 3
1&
#90
b11 +
b11 .
b11 <
b1000 '
b1000 *
b1000 ;
b1001001000 =
b1000 >
0&
#95
b11 1
12
1)
1&
#100
0)
0&
#105
02
15
b1101 3
1&
#110
0&
#115
17
b11 0
05
b11011 3
1&
#120
b10010010001000 =
0&
#125
b1 6
12
1)
1&
#130
0)
0&
#135
07
02
15
b110111 3
1&
#140
0&
#145
b0 6
07
b100 0
05
b1101111 3
1&
#150
0&
#155
b1 +
b1 .
b1 <
b10 '
b10 *
b10 ;
b10 >
b10 =
1&
#160
0&
#165
b1 1
12
1)
1&
#170
0)
0&
#175
02
15
b11011110 3
1&
#180
0&
#185
17
b101 0
05
b10111101 3
1&
#190
b0 +
b0 .
b0 <
b1 '
b1 *
b1 ;
b100001 =
b1 >
0&
#195
b1 6
b0 1
12
1)
1&
#200
0)
0&
#205
07
02
15
b1111010 3
1&
#210
0&
#215
b0 6
07
b110 0
05
b11110100 3
1&
#220
b11 +
b11 .
b11 <
b1000 '
b1000 *
b1000 ;
b1000011000 =
b1000 >
0&
#225
b11 1
12
1)
1&
#230
0)
0&
#235
02
15
b11101001 3
1&
#240
0&
#245
17
b111 0
05
b11010011 3
1&
#250
b10000110001000 =
0&
#255
b1 6
12
1)
1&
#260
0)
0&
#265
07
02
15
b10100111 3
1&
#270
0&
#275
b0 6
07
b0 0
05
b1001111 3
1&
#280
0&
#285
b1 +
b1 .
b1 <
b10 '
b10 *
b10 ;
b10 >
b10 =
1&
#290
0&
#295
b1 1
12
1)
1&
#300
0)
0&
#305
02
15
b10011110 3
1&
#310
0&
#315
17
b1 0
05
b111101 3
1&
#320
b100010 =
0&
#325
b1 6
12
1)
1&
#330
0)
0&
#335
07
02
15
b1111010 3
1&
#340
0&
#345
b0 6
07
b10 0
05
b11110101 3
1&
#350
b1000100010 =
0&
#355
12
1)
1&
#360
0)
0&
#365
02
15
b11101010 3
1&
#370
0&
#375
17
b11 0
05
b11010101 3
1&
#380
b10001000100010 =
0&
#385
b1 6
12
1)
1&
#390
0)
0&
#395
07
02
15
b10101010 3
1&
#400
0&
#405
b0 6
07
b100 0
05
b1010101 3
1&
#410
0&
#415
b0 +
b0 .
b0 <
b1 '
b1 *
b1 ;
b1 >
b1 =
1&
#420
0&
#425
b0 1
12
1)
1&
#430
0)
0&
#435
02
15
b10101010 3
1&
#440
0&
#445
17
b101 0
05
b1010100 3
1&
#450
b10001 =
0&
#455
b1 6
12
1)
1&
#460
0)
0&
#465
07
02
15
b10101000 3
1&
#470
0&
#475
b0 6
07
b110 0
05
b1010000 3
1&
#480
b100010001 =
0&
#485
12
1)
1&
#490
0)
0&
#495
02
15
b10100000 3
1&
#500
0&
#505
17
b111 0
05
b1000000 3
1&
#510
b10 +
b10 .
b10 <
b100 '
b100 *
b100 ;
b1000100010100 =
b100 >
0&
#515
b1 6
b10 1
12
1)
1&
#520
0)
0&
#525
07
02
15
b10000001 3
1&
#530
0&
#535
b0 6
07
b0 0
05
b10 3
1&
#540
0&
#545
b100 =
1&
#550
0&
#555
12
1)
1&
#560
0)
0&
#565
02
15
b101 3
1&
#570
0&
#575
17
b1 0
05
b1010 3
1&
#580
b1000100 =
0&
#585
b1 6
12
1)
1&
#590
0)
0&
#595
07
02
15
b10101 3
1&
#600
0&
#605
b0 6
07
b10 0
05
b101010 3
1&
#610
b0 +
b0 .
b0 <
b1 '
b1 *
b1 ;
b10001000001 =
b1 >
0&
#615
b0 1
12
1)
1&
#620
0)
0&
#625
02
15
b1010100 3
1&
#630
0&
#635
17
b11 0
05
b10101000 3
1&
#640
b11 +
b11 .
b11 <
b1000 '
b1000 *
b1000 ;
b100010000011000 =
b1000 >
0&
#645
b1 6
b11 1
12
1)
1&
#650
0)
0&
#655
07
02
15
b1010001 3
1&
#660
0&
#665
b0 6
07
b100 0
05
b10100011 3
1&
#670
0&
#675
b1000 =
1&
#680
0&
#685
12
1)
1&
#690
0)
0&
#695
02
15
b1000111 3
1&
#700
0&
#705
17
b101 0
05
b10001111 3
1&
#710
b0 +
b0 .
b0 <
b1 '
b1 *
b1 ;
b10000001 =
b1 >
0&
#715
b1 6
b0 1
12
1)
1&
#720
0)
0&
#725
07
02
15
b11110 3
1&
#730
0&
#735
b0 6
07
b110 0
05
b111100 3
1&
#740
b100000010001 =
0&
#745
12
1)
1&
#750
0)
0&
#755
02
15
b1111000 3
1&
#760
0&
#765
17
b111 0
05
b11110000 3
1&
#770
b10 +
b10 .
b10 <
b100 '
b100 *
b100 ;
b1000000100010100 =
b100 >
0&
#775
b1 6
b10 1
12
1)
1&
#780
0)
0&
#785
07
02
15
b11100001 3
1&
#790
0&
#795
b0 6
07
b0 0
05
b11000010 3
1&
#800
0&
#805
b100 =
1&
#810
0&
#815
12
1)
1&
#820
0)
0&
#825
02
15
b10000101 3
1&
#830
0&
#835
17
b1 0
05
b1010 3
1&
#840
b1000100 =
0&
#845
b1 6
12
1)
1&
#850
0)
0&
#855
07
02
15
b10101 3
1&
#860
0&
#865
b0 6
07
b10 0
05
b101010 3
1&
#870
b1 +
b1 .
b1 <
b10 '
b10 *
b10 ;
b10001000010 =
b10 >
0&
#875
b1 1
12
1)
1&
#880
0)
0&
#885
02
15
b1010100 3
1&
#890
0&
#895
17
b11 0
05
b10101001 3
1&
#900
b10 +
b10 .
b10 <
b100 '
b100 *
b100 ;
b100010000100100 =
b100 >
0&
#905
b1 6
b10 1
12
1)
1&
#910
0)
0&
#915
07
02
15
b1010011 3
1&
#920
0&
#925
b0 6
07
b100 0
05
b10100110 3
1&
#930
0&
#935
b11 +
b11 .
b11 <
b1000 '
b1000 *
b1000 ;
b1000 >
b1000 =
1&
#940
0&
#945
b11 1
12
1)
1&
#950
0)
0&
#955
02
15
b1001101 3
1&
#960
0&
#965
17
b101 0
05
b10011011 3
1&
#970
b10001000 =
0&
#975
b1 6
12
1)
1&
#980
0)
0&
#985
07
02
15
b110111 3
1&
#990
0&
#995
b0 6
07
b110 0
05
b1101111 3
1&
#1000
b100010001000 =
0&
#1005
12
1)
1&
#1010
0)
0&
#1015
02
15
b11011111 3
1&
#1020
0&
#1025
17
b111 0
05
b10111111 3
1&
#1030
b1 +
b1 .
b1 <
b10 '
b10 *
b10 ;
b1000100010000010 =
b10 >
0&
#1035
b1 6
b1 1
12
1)
1&
#1040
0)
0&
#1045
07
02
15
b1111110 3
1&
#1050
0&
#1055
b0 6
07
b0 0
05
b11111101 3
1&
#1060
0&
#1065
b10 +
b10 .
b10 <
b100 '
b100 *
b100 ;
b100 >
b100 =
1&
#1070
0&
#1075
b10 1
12
1)
1&
#1080
0)
0&
#1085
02
15
b11111011 3
1&
#1090
0&
#1095
17
b1 0
05
b11110110 3
1&
#1100
b1 +
b1 .
b1 <
b10 '
b10 *
b10 ;
b1000010 =
b10 >
0&
#1105
b1 6
b1 1
12
1)
1&
#1110
0)
0&
#1115
07
02
15
b11101100 3
1&
#1120
0&
#1125
b0 6
07
b10 0
05
b11011001 3
1&
#1130
b0 +
b0 .
b0 <
b1 '
b1 *
b1 ;
b10000100001 =
b1 >
0&
#1135
b0 1
12
1)
1&
#1140
0)
0&
#1145
02
15
b10110010 3
1&
#1150
0&
#1155
17
b11 0
05
b1100100 3
1&
#1160
b10 +
b10 .
b10 <
b100 '
b100 *
b100 ;
b100001000010100 =
b100 >
0&
#1165
b1 6
b10 1
12
1)
1&
#1170
0)
0&
#1175
07
02
15
b11001001 3
1&
#1180
0&
#1185
b0 6
07
b100 0
05
b10010010 3
1&
#1190
0&
#1195
b100 =
1&
#1200
0&
#1205
12
1)
1&
#1210
0)
0&
#1215
02
15
b100101 3
1&
#1220
0&
#1225
17
b101 0
05
b1001010 3
1&
#1230
b11 +
b11 .
b11 <
b1000 '
b1000 *
b1000 ;
b1001000 =
b1000 >
0&
#1235
b1 6
b11 1
12
1)
1&
#1240
0)
0&
#1245
07
02
15
b10010101 3
1&
#1250
0&
#1255
b0 6
07
b110 0
05
b101011 3
1&
#1260
b10010001000 =
0&
#1265
12
1)
1&
#1270
0)
0&
#1275
02
15
b1010111 3
1&
#1280
0&
#1285
17
b111 0
05
b10101111 3
1&
#1290
b100100010001000 =
0&
#1295
b1 6
12
1)
1&
#1300
0)
0&
#1305
07
02
15
b1011111 3
1&
#1310
0&
#1315
b0 6
07
b0 0
05
b10111111 3
1&
#1320
0&
#1325
b1 +
b1 .
b1 <
b10 '
b10 *
b10 ;
b10 >
b10 =
1&
#1330
0&
#1335
b1 1
12
1)
1&
#1340
0)
0&
#1345
02
15
b1111110 3
1&
#1350
0&
#1355
17
b1 0
05
b11111101 3
1&
#1360
b10 +
b10 .
b10 <
b100 '
b100 *
b100 ;
b100100 =
b100 >
0&
#1365
b1 6
b10 1
12
1)
1&
#1370
0)
0&
#1375
07
02
15
b11111011 3
1&
#1380
0&
#1385
b0 6
07
b10 0
05
b11110110 3
1&
#1390
b11 +
b11 .
b11 <
b1000 '
b1000 *
b1000 ;
b1001001000 =
b1000 >
0&
#1395
b11 1
12
1)
1&
#1400
0)
0&
#1405
02
15
b11101101 3
1&
#1410
0&
#1415
17
b11 0
05
b11011011 3
1&
#1420
b10 +
b10 .
b10 <
b100 '
b100 *
b100 ;
b10010010000100 =
b100 >
0&
#1425
b1 6
b10 1
12
1)
1&
#1430
0)
0&
#1435
07
02
15
b10110111 3
1&
#1440
0&
#1445
b0 6
07
b100 0
05
b1101110 3
1&
#1450
0&
#1455
b1 +
b1 .
b1 <
b10 '
b10 *
b10 ;
b10 >
b10 =
1&
#1460
0&
#1465
b1 1
12
1)
1&
#1470
0)
0&
#1475
02
15
b11011100 3
1&
#1480
0&
#1485
17
b101 0
05
b10111001 3
1&
#1490
b10 +
b10 .
b10 <
b100 '
b100 *
b100 ;
b100100 =
b100 >
0&
#1495
b1 6
b10 1
12
1)
1&
#1500
0)
0&
#1505
07
02
15
b1110011 3
1&
#1510
0&
#1515
b0 6
07
b110 0
05
b11100110 3
1&
#1520
b1 +
b1 .
b1 <
b10 '
b10 *
b10 ;
b1001000010 =
b10 >
0&
#1525
b1 1
12
1)
1&
#1530
0)
0&
#1535
02
15
b11001100 3
1&
#1540
0&
#1545
17
b111 0
05
b10011001 3
1&
#1550
b10010000100010 =
0&
#1555
b1 6
12
1)
1&
#1560
0)
0&
#1565
07
02
15
b110010 3
1&
#1570
0&
#1575
b0 6
07
b0 0
05
b1100101 3
1&
#1580
0&
#1585
b10 +
b10 .
b10 <
b100 '
b100 *
b100 ;
b100 >
b100 =
1&
#1590
0&
#1595
b10 1
12
1)
1&
#1600
0)
0&
#1605
02
15
b11001011 3
1&
#1610
0&
#1615
17
b1 0
05
b10010110 3
1&
#1620
b11 +
b11 .
b11 <
b1000 '
b1000 *
b1000 ;
b1001000 =
b1000 >
0&
#1625
b1 6
b11 1
12
1)
1&
#1630
0)
0&
#1635
07
02
15
b101101 3
1&
#1640
0&
#1645
b0 6
07
b10 0
05
b1011011 3
1&
#1650
b0 +
b0 .
b0 <
b1 '
b1 *
b1 ;
b10010000001 =
b1 >
0&
#1655
b0 1
12
1)
1&
#1660
0)
0&
#1665
02
15
b10110110 3
1&
#1670
0&
#1675
17
b11 0
05
b1101100 3
1&
#1680
b100100000010001 =
0&
#1685
b1 6
12
1)
1&
#1690
0)
0&
#1695
07
02
15
b11011000 3
1&
#1700
0&
#1705
b0 6
07
b100 0
05
b10110000 3
1&
#1710
0&
#1715
b1 +
b1 .
b1 <
b10 '
b10 *
b10 ;
b10 >
b10 =
1&
#1720
0&
#1725
b1 1
12
1)
1&
#1730
0)
0&
#1735
02
15
b1100000 3
1&
#1740
0&
#1745
17
b101 0
05
b11000001 3
1&
#1750
b10 +
b10 .
b10 <
b100 '
b100 *
b100 ;
b100100 =
b100 >
0&
#1755
b1 6
b10 1
12
1)
1&
#1760
0)
0&
#1765
07
02
15
b10000011 3
1&
#1770
0&
#1775
b0 6
07
b110 0
05
b110 3
1&
#1780
b1 +
b1 .
b1 <
b10 '
b10 *
b10 ;
b1001000010 =
b10 >
0&
#1785
b1 1
12
1)
1&
#1790
0)
0&
#1795
02
15
b1100 3
1&
#1800
0&
#1805
17
b111 0
05
b11001 3
1&
#1810
b10 +
b10 .
b10 <
b100 '
b100 *
b100 ;
b10010000100100 =
b100 >
0&
#1815
b1 6
b10 1
12
1)
1&
#1820
0)
0&
#1825
07
02
15
b110011 3
1&
#1830
0&
#1835
b0 6
07
b0 0
05
b1100110 3
1&
#1840
0&
#1845
b0 +
b0 .
b0 <
b1 '
b1 *
b1 ;
b1 >
b1 =
1&
#1850
0&
#1855
b0 1
12
1)
1&
#1860
0)
0&
#1865
02
15
b11001100 3
1&
#1870
0&
#1875
17
b1 0
05
b10011000 3
1&
#1880
b10001 =
0&
#1885
b1 6
12
1)
1&
#1890
0)
0&
#1895
07
02
15
b110000 3
1&
#1900
0&
#1905
b0 6
07
b10 0
05
b1100000 3
1&
#1910
b100010001 =
0&
#1915
12
1)
1&
#1920
0)
0&
#1925
02
15
b11000000 3
1&
#1930
0&
#1935
17
b11 0
05
b10000000 3
1&
#1940
b1000100010001 =
0&
#1945
b1 6
12
1)
1&
#1950
0)
0&
#1955
07
02
15
b0 3
1&
#1960
0&
#1965
b0 6
07
b100 0
05
1&
#1970
0&
#1975
b10 +
b10 .
b10 <
b100 '
b100 *
b100 ;
b100 >
b100 =
1&
#1980
0&
#1985
b10 1
12
1)
1&
#1990
0)
0&
#1995
02
15
b1 3
1&
#2000
0&
#2005
17
b101 0
05
b10 3
1&
#2010
b1 +
b1 .
b1 <
b10 '
b10 *
b10 ;
b1000010 =
b10 >
0&
#2015
b1 6
b1 1
12
1)
1&
#2020
0)
0&
#2025
07
02
15
b100 3
1&
#2030
0&
#2035
b0 6
07
b110 0
05
b1001 3
1&
#2040
b11 +
b11 .
b11 <
b1000 '
b1000 *
b1000 ;
b10000101000 =
b1000 >
0&
#2045
b11 1
12
1)
1&
#2050
0)
0&
#2055
02
15
b10011 3
1&
#2060
0&
#2065
17
b111 0
05
b100111 3
1&
#2070
b100001010001000 =
0&
#2075
b1 6
12
1)
1&
#2080
0)
0&
#2085
07
02
15
b1001111 3
1&
#2090
0&
#2095
b0 6
07
b0 0
05
b10011111 3
1&
#2100
0&
#2105
b0 +
b0 .
b0 <
b1 '
b1 *
b1 ;
b1 >
b1 =
1&
#2110
0&
#2115
b0 1
12
1)
1&
#2120
0)
0&
#2125
02
15
b111110 3
1&
#2130
0&
#2135
17
b1 0
05
b1111100 3
1&
#2140
b1 +
b1 .
b1 <
b10 '
b10 *
b10 ;
b10010 =
b10 >
0&
#2145
b1 6
b1 1
12
1)
1&
#2150
0)
0&
#2155
07
02
15
b11111000 3
1&
#2160
0&
#2165
b0 6
07
b10 0
05
b11110001 3
1&
#2170
b11 +
b11 .
b11 <
b1000 '
b1000 *
b1000 ;
b100101000 =
b1000 >
0&
#2175
b11 1
12
1)
1&
#2180
0)
0&
#2185
02
15
b11100011 3
1&
#2190
0&
#2195
17
b11 0
05
b11000111 3
1&
#2200
b1 +
b1 .
b1 <
b10 '
b10 *
b10 ;
b1001010000010 =
b10 >
0&
#2205
b1 6
b1 1
12
1)
1&
#2210
0)
0&
#2215
07
02
15
b10001110 3
1&
#2220
0&
#2225
b0 6
07
b100 0
05
b11101 3
1&
#2230
0&
#2235
b11 +
b11 .
b11 <
b1000 '
b1000 *
b1000 ;
b1000 >
b1000 =
1&
#2240
0&
#2245
b11 1
12
1)
1&
#2250
0)
0&
#2255
02
15
b111011 3
1&
#2260
0&
#2265
17
b101 0
05
b1110111 3
1&
#2270
b1 +
b1 .
b1 <
b10 '
b10 *
b10 ;
b10000010 =
b10 >
0&
#2275
b1 6
b1 1
12
1)
1&
#2280
0)
0&
#2285
07
02
15
b11101110 3
1&
#2290
0&
#2295
b0 6
07
b110 0
05
b11011101 3
1&
#2300
b0 +
b0 .
b0 <
b1 '
b1 *
b1 ;
b100000100001 =
b1 >
0&
#2305
b0 1
12
1)
1&
#2310
0)
0&
#2315
02
15
b10111010 3
1&
#2320
0&
#2325
17
b111 0
05
b1110100 3
1&
#2330
b1000001000010001 =
0&
#2335
b1 6
12
1)
1&
#2340
0)
0&
#2345
07
02
15
b11101000 3
1&
#2350
0&
#2355
b0 6
07
b0 0
05
b11010000 3
1&
#2360
0&
#2365
b1 +
b1 .
b1 <
b10 '
b10 *
b10 ;
b10 >
b10 =
1&
#2370
0&
#2375
b1 1
12
1)
1&
#2380
0)
0&
#2385
02
15
b10100000 3
1&
#2390
0&
#2395
17
b1 0
05
b1000001 3
1&
#2400
b100010 =
0&
#2405
b1 6
12
1)
1&
#2410
0)
0&
#2415
07
02
15
b10000010 3
1&
#2420
0&
#2425
b0 6
07
b10 0
05
b101 3
1&
#2430
b0 +
b0 .
b0 <
b1 '
b1 *
b1 ;
b1000100001 =
b1 >
0&
#2435
b0 1
12
1)
1&
#2440
0)
0&
#2445
02
15
b1010 3
1&
#2450
0&
#2455
17
b11 0
05
b10100 3
1&
#2460
b10001000010001 =
0&
#2465
b1 6
12
1)
1&
#2470
0)
0&
#2475
07
02
15
b101000 3
1&
#2480
0&
#2485
b0 6
07
b100 0
05
b1010000 3
1&
#2490
0&
#2495
b1 =
1&
#2500
0&
#2505
12
1)
1&
#2510
0)
0&
#2515
02
15
b10100000 3
1&
#2520
0&
#2525
17
b101 0
05
b1000000 3
1&
#2530
b10 +
b10 .
b10 <
b100 '
b100 *
b100 ;
b10100 =
b100 >
0&
#2535
b1 6
b10 1
12
1)
1&
#2540
0)
0&
#2545
07
02
15
b10000001 3
1&
#2550
0&
#2555
b0 6
07
b110 0
05
b10 3
1&
#2560
b101000100 =
0&
#2565
12
1)
1&
#2570
0)
0&
#2575
02
15
b101 3
1&
#2580
0&
#2585
17
b111 0
05
b1010 3
1&
#2590
b11 +
b11 .
b11 <
b1000 '
b1000 *
b1000 ;
b1010001001000 =
b1000 >
0&
#2595
b1 6
b11 1
12
1)
1&
#2600
0)
0&
#2605
07
02
15
b10101 3
1&
#2610
0&
#2615
b0 6
07
b0 0
05
b101011 3
1&
#2620
0&
#2625
b1000 =
1&
#2630
0&
#2635
12
1)
1&
#2640
0)
0&
#2645
02
15
b1010111 3
1&
#2650
0&
#2655
17
b1 0
05
b10101111 3
1&
#2660
b0 +
b0 .
b0 <
b1 '
b1 *
b1 ;
b10000001 =
b1 >
0&
#2665
b1 6
b0 1
12
1)
1&
#2670
0)
0&
#2675
07
02
15
b1011110 3
1&
#2680
0&
#2685
b0 6
07
b10 0
05
b10111100 3
1&
#2690
b11 +
b11 .
b11 <
b1000 '
b1000 *
b1000 ;
b100000011000 =
b1000 >
0&
#2695
b11 1
12
1)
1&
#2700
0)
0&
#2705
02
15
b1111001 3
1&
#2710
0&
#2715
17
b11 0
05
b11110011 3
1&
#2720
b10 +
b10 .
b10 <
b100 '
b100 *
b100 ;
b1000000110000100 =
b100 >
0&
#2725
b1 6
b10 1
12
1)
1&
#2730
0)
0&
#2735
07
02
15
b11100111 3
1&
#2740
0&
#2745
b0 6
07
b100 0
05
b11001110 3
1&
#2750
0&
#2755
b100 =
1&
#2760
0&
#2765
12
1)
1&
#2770
0)
0&
#2775
02
15
b10011101 3
1&
#2780
0&
#2785
17
b101 0
05
b111010 3
1&
#2790
b11 +
b11 .
b11 <
b1000 '
b1000 *
b1000 ;
b1001000 =
b1000 >
0&
#2795
b1 6
b11 1
12
1)
1&
#2800
0)
0&
#2805
07
02
15
b1110101 3
1&
#2810
0&
#2815
b0 6
07
b110 0
05
b11101011 3
1&
#2820
b0 +
b0 .
b0 <
b1 '
b1 *
b1 ;
b10010000001 =
b1 >
0&
#2825
b0 1
12
1)
1&
#2830
0)
0&
#2835
02
15
b11010110 3
1&
#2840
0&
#2845
17
b111 0
05
b10101100 3
1&
#2850
b1 +
b1 .
b1 <
b10 '
b10 *
b10 ;
b100100000010010 =
b10 >
0&
#2855
b1 6
b1 1
12
1)
1&
#2860
0)
0&
#2865
07
02
15
b1011000 3
1&
#2870
0&
#2875
b0 6
07
b0 0
05
b10110001 3
1&
#2880
0&
#2885
b10 +
b10 .
b10 <
b100 '
b100 *
b100 ;
b100 >
b100 =
1&
#2890
0&
#2895
b10 1
12
1)
1&
#2900
0)
0&
#2905
02
15
b1100011 3
1&
#2910
0&
#2915
17
b1 0
05
b11000110 3
1&
#2920
b0 +
b0 .
b0 <
b1 '
b1 *
b1 ;
b1000001 =
b1 >
0&
#2925
b1 6
b0 1
12
1)
1&
#2930
0)
0&
#2935
07
02
15
b10001100 3
1&
#2940
0&
#2945
b0 6
07
b10 0
05
b11000 3
1&
#2950
b11 +
b11 .
b11 <
b1000 '
b1000 *
b1000 ;
b10000011000 =
b1000 >
0&
#2955
b11 1
12
1)
1&
