DUT/HoldLED.v

module HoldLED #(parameter length= 250_000_000)(
	input clk,reset,
	output reg LED
	);
	
	reg [27:0] counter;
	
	always @(posedge clk)begin
		if(reset) begin
			counter<=0;
			LED <=1;
			

		end else if(counter<length)begin
			LED<=1;
			counter<= counter+1;
		end else begin
			LED<=0;
		end
		
	end
endmodule

DUT/PinCheck.v


module PinCheck #(parameter passkey = 8'b10100101)(
    input [1:0] digit,
    input submit, reset, clk,
    output reg waiting, correct, incorrect,bug
);
    reg [2:0] state;
	reg verify;
	reg [2:0] dig_count;
	reg [7:0] password;
	reg firstDigit,secondDigit;
	reg right_wrong_in,right_wrong_out;
	reg [1:0] digit_stw;
	 
//Instantiate LED holding
	 HoldLED holdLED(
		.clk(clk),
		.reset(right_wrong_in),
		.LED(right_wrong_out)
	 );

 //state reset
		always @(posedge clk or posedge reset) begin
		  if(reset) begin
				state <= 0;
				correct<=0;
				incorrect<=0;
				bug<=0;
		  end
		end
		
//pinloading
		always @(posedge clk) begin
			if(reset) begin
				password <= 0;
				dig_count<=0;
				verify<=0;
			end else if(firstDigit) begin
				password <= {password[6:0],digit_stw[1]};
				secondDigit<=1;
				firstDigit<=0;
			end else if(secondDigit) begin
				password <= {password[6:0],digit_stw[0]};
				secondDigit<=0;
				dig_count<= dig_count+1;
				state<=1;
			end else if (submit) begin
				firstDigit<=1;
				digit_stw<=digit;

			end
		end


//fsm logic
		always @(posedge clk or posedge reset) begin
		  case(state)
			0:begin//Default state
				waiting<=1;
				verify<=0;
			end
			1:begin//Digit read state
				if(dig_count==4) begin//if all digits are read, move to next state
					state <= 2;
					waiting<=0;
					verify<=1;
					dig_count<=0;
				end 
			end
			2:begin//all digits have been read, 
			//TODO: verified timing logic with timing chart, need to decide what state 2 is.
			//Next step would be verification so i need to think about what verification logic will be and how it should relate to flags like waiting or other leds
			//waiting turns to 0 when update is assigned 2. Is this ideal? state only changes 2 cycles after update changes this should be considered.
				if(password == passkey) begin
					state <=3;
				end else begin
					state<=4;
				end
				verify<=0;
			end
			
			3:begin//correct password
				right_wrong_in<=1;
				correct<=1;
				state<=5;
				
			end
			
			4:begin//incorrect password
				right_wrong_in<=1;
				incorrect<=1;
				state<=5;
			end
			
			5:begin//Holding LED
				right_wrong_in<=0;
				if(right_wrong_out!=1) begin
					state<=0;
					correct<=0;
					incorrect<=0;
				end
					
			end
			
			default:begin
				bug<=1;
			end
		  endcase
		end


    
    

    

endmodule

DUT/Encoder.v
module priorityEncoder(
	input [3:0] in,
	output reg [1:0] out
	);
	
	
	always @(*)begin
      casez(in)
		4'b1???:out=3;
		4'b01??:out=2;
		4'b001?:out=1;
		4'b0001:out=0;
		default:begin
			out=1'bx;
			end
		endcase
	end
	
endmodule

DUT/DebitPin.v


module DebitPin #(parameter passkey = 4'b1010)(
    input digit_switches[3:0],
    input clk, reset, submit,
    output reg waiting, correct, incorrect,bug
);

    wire [1:0] digit;

    priorityEncoder priority_enc(
        .in(digit_switches),
        .out(digit)

    );

    PinCheck pinchk(
        .digit(digit),
        .submit(submit), .reset(reset), .clk(clk),
        .waiting(waiting), .correct(correct), .incorrect(incorrect),.bug(bug)
    );


endmodule

Testbench/tb_DebitPin/tb_top.sv
`ifndef passkey
    `define passkey  8'b10100101
`endif


//Iverilog doesn't support constraints and random variable type :(
// class digit_item;

//     randc bit [3:0] digit;

//     constraint digit_lim {((digit == 4'b1000)||(digit == 4'b0100)||(digit == 4'b0010)||(digit == 4'b0001));}

//     function void print(string tag="");
//         $display("T=%0t [%s] digit=%0d",$time,digit);
//     endfunction
// endclass

module top();

    parameter passkey = `passkey;
   

    logic [3:0] digits;
    logic clk, reset, submit, waiting, correct, incorrect, bug;
    

    DebitPin #(passkey) debitpin(
        .digit_switches(digits),
        .clk(clk),
        .reset(reset),
        .submit(submit),
        .waiting(waiting),
        .correct(correct),
        .incorrect(incorrect),
        .bug(bug)
    );

    function automatic logic [1:0] encode (input logic [3:0] in);
        casez(in)
            4'b1???:encode = 2'd3;
            4'b01??:encode = 2'd2;
            4'b001?:encode = 2'd1;
            4'b0001:encode = 2'd0;
            default: encode = 2'bxx;
        endcase
    endfunction

     function automatic logic [3:0] decode (input logic [1:0] in);
        casez(in)
            2'd3:decode = 4'b1000;
            2'd2:decode = 4'b0100;
            2'd1:decode = 4'b0010;
            2'd0:decode = 4'b0001;
            default: decode = 4'bx;
        endcase
    endfunction

    task DigitSubmission();//implement this testbench
        static bit [3:0] allowed_digits [0:3];
        logic [15:0] password;
        begin
            
            allowed_digits[0] = 4'b1000;
            allowed_digits[1] = 4'b0100;
            allowed_digits[2] = 4'b0010;
            allowed_digits[3] = 4'b0001;
            //for each digit
            repeat(24) @(posedge clk) begin
                password = 16'b0;

                repeat(4) begin
                    //randomize passkey selection
                    bit [3:0] digit;
                    digit = allowed_digits[$urandom_range(0, 3)];

                    //Track digits submitted
                    password = {password[11:0],digit};

                    //submit random digit
                    digits = digit;
                    @(posedge clk);
                        submit = 1;
                    @(negedge clk);
                        submit = 0;
                    //allow pincheck logic to update
                    repeat(2) begin
                        @(negedge clk);
                    end
                    //observe statemachine progression
                    $display("T=%0t,passowrd = %0b,encode=%0b",$time,password[15:12],encode(password[15:12]));
                    $display("passowrd = %0b,encode=%0b",password[11:8],encode(password[11:8]));
                    $display("passowrd = %0b,encode=%0b",password[7:4],encode(password[7:4]));
                    $display("passowrd = %0b,encode=%0b",password[3:0],encode(password[3:0]));
                end
                assert(encode(password[15:12]) ==debitpin.pinchk.password[7:6]);
                assert(encode(password[11:8]) ==debitpin.pinchk.password[5:4]);
                assert(encode(password[7:4]) ==debitpin.pinchk.password[3:2]);
                assert(encode(password[3:0]) ==debitpin.pinchk.password[1:0]);
            end
        end

    endtask

   
    task PasswordVerification();
    begin
            logic [15:0] password;
            
            password[15:12] = decode(passkey[7:6]);
            password[11:8] = decode(passkey[5:4]);
            password[7:4] = decode(passkey[3:2]);
            password[3:0] = decode(passkey[1:0]);

            repeat(4) @(posedge clk) begin
                //randomize passkey selection
                bit [3:0] digit;


                //submit random digit
                digits = password[15:12];
                password = {password[11:0],4'b0};

                @(posedge clk);
                    submit = 1;
                @(negedge clk);
                    submit = 0;
                //allow pincheck logic to update
                repeat(2) begin
                    @(negedge clk);
                end
                //observe statemachine progression
                $display("T=%0t,passowrd = %0b",$time,password);
                
            end
            assert(password==0);        
            assert(debitpin.pinchk.dig_count==4);
            
            @(negedge clk);
                assert(debitpin.pinchk.dig_count == 0); 
                assert(debitpin.pinchk.verify == 1);
                assert(waiting==0);    
            @(negedge clk); 
                assert(debitpin.pinchk.state==3);
            @(negedge clk); 
                assert(debitpin.pinchk.state==5);
                assert(correct==1);
                assert(incorrect ==0);
                assert(bug==0);
        end
    endtask


    initial begin
        clk = 0;
        forever #5 clk = ~clk;
    end

    initial begin
        $dumpfile("dump.vcd");
        $dumpvars();
        $dumpvars(0,debitpin.pinchk);

        @(negedge clk);
            reset = 1;
        @(negedge clk);
            reset = 0;

        // DigitSubmission();


        PasswordVerification();

        $finish();
    end

endmodule

//TODO: Testbench for pinverify low key is correct but the state update mechanism is convoluted and could be simplified. Aim to do so next time. Specifically
//The state oscilalted bwteen 0 and 1 and so it creates a cycle delay before it can move on to state 2/3
//may be an issue may not- but see if i can simplify logic

dump.vcd
$date
	Tue Aug 12 19:37:48 2025
$end
$version
	Icarus Verilog
$end
$timescale
	1s
$end
$scope module top $end
$var wire 1 ! waiting $end
$var wire 1 " incorrect $end
$var wire 1 # correct $end
$var wire 1 $ bug $end
$var parameter 8 % passkey $end
$var reg 1 & clk $end
$var reg 4 ' digits [3:0] $end
$var reg 1 ( reset $end
$var reg 1 ) submit $end
$scope function decode $end
$upscope $end
$scope function encode $end
$upscope $end
$scope module debitpin $end
$var wire 1 & clk $end
$var wire 4 * digit_switches [3:0] $end
$var wire 1 ( reset $end
$var wire 1 ) submit $end
$var wire 1 ! waiting $end
$var wire 1 " incorrect $end
$var wire 2 + digit [1:0] $end
$var wire 1 # correct $end
$var wire 1 $ bug $end
$var parameter 8 , passkey $end
$scope module pinchk $end
$var wire 1 & clk $end
$var wire 1 ( reset $end
$var wire 1 ) submit $end
$var wire 1 - right_wrong_out $end
$var wire 2 . digit [1:0] $end
$var parameter 8 / passkey $end
$var reg 1 $ bug $end
$var reg 1 # correct $end
$var reg 3 0 dig_count [2:0] $end
$var reg 2 1 digit_stw [1:0] $end
$var reg 1 2 firstDigit $end
$var reg 1 " incorrect $end
$var reg 8 3 password [7:0] $end
$var reg 1 4 right_wrong_in $end
$var reg 1 5 secondDigit $end
$var reg 3 6 state [2:0] $end
$var reg 1 7 verify $end
$var reg 1 ! waiting $end
$scope module holdLED $end
$var wire 1 & clk $end
$var wire 1 4 reset $end
$var parameter 32 8 length $end
$var reg 1 - LED $end
$var reg 28 9 counter [27:0] $end
$upscope $end
$upscope $end
$scope module priority_enc $end
$var wire 4 : in [3:0] $end
$var reg 2 ; out [1:0] $end
$upscope $end
$upscope $end
$scope task DigitSubmission $end
$var reg 16 < password [15:0] $end
$scope begin $unm_blk_28 $end
$var reg 4 = digit [3:0] $end
$upscope $end
$upscope $end
$scope task PasswordVerification $end
$scope begin $unm_blk_30 $end
$var reg 16 > password [15:0] $end
$scope begin $unm_blk_31 $end
$upscope $end
$upscope $end
$upscope $end
$upscope $end
$scope module top $end
$scope module debitpin $end
$scope module pinchk $end
$scope module holdLED $end
$upscope $end
$upscope $end
$upscope $end
$upscope $end
$enddefinitions $end
$comment Show the parameter values. $end
$dumpall
b1110111001101011001010000000 8
b10100101 /
b10100101 ,
b10100101 %
$end
#0
$dumpvars
bx >
b0 =
bx <
bx ;
bx :
bx 9
x7
bx 6
x5
x4
bx 3
x2
bx 1
bx 0
bx .
x-
bx +
bx *
x)
x(
bx '
0&
x$
x#
x"
x!
$end
#5
1$
0-
1&
#10
1$
0"
0#
b0 6
1(
0&
#15
0$
1!
07
b0 0
b0 3
1&
#20
b100010000100010 >
0(
0&
#25
b10 +
b10 .
b10 ;
b100001000100000 >
b100 '
b100 *
b100 :
1&
#30
0&
#35
b10 1
12
1)
1&
#40
0)
0&
#45
02
15
b1 3
1&
#50
0&
#55
b1 6
b1 0
05
b10 3
1&
#60
0&
#65
b10001000000000 >
1&
#70
0&
#75
12
1)
1&
#80
0)
0&
#85
02
15
b101 3
1&
#90
0&
#95
b10 0
05
b1010 3
1&
#100
0&
#105
b1 +
b1 .
b1 ;
b10000000000000 >
b10 '
b10 *
b10 :
1&
#110
0&
#115
b1 1
12
1)
1&
#120
0)
0&
#125
02
15
b10100 3
1&
#130
0&
#135
b11 0
05
b101001 3
1&
#140
0&
#145
b0 >
1&
#150
0&
#155
12
1)
1&
#160
0)
0&
#165
02
15
b1010010 3
1&
#170
0&
#175
b100 0
05
b10100101 3
1&
#180
0&
#185
b0 0
17
0!
b10 6
1&
#190
0&
#195
07
b11 6
1&
#200
0&
#205
b101 6
1#
14
1&
