DUT/HoldLED.v

module HoldLED #(parameter length= 250_000_000)(
	input clk,reset,
	output reg LED
	);
	
	reg [27:0] counter;
	
	always @(posedge clk)begin
		if(reset) begin
			counter<=0;
			LED <=1;
			

		end else if(counter<length)begin
			LED<=1;
			counter<= counter+1;
		end else begin
			LED<=0;
		end
		
	end
endmodule

DUT/PinCheck.v


module PinCheck #(parameter passkey = 4'b1010)(
    input [1:0] digit,
    input submit, reset, clk,
    output reg waiting, correct, incorrect,bug
);
    reg [2:0] state;
	reg update,verify;
	reg [2:0] dig_count;
	reg [7:0] password;
	reg firstDigit,secondDigit;
	reg right_wrong_in,right_wrong_out;
	 
//Instantiate LED holding
	 HoldLED holdLED(
		.clk(clk),
		.reset(right_wrong_in),
		.LED(right_wrong_out)
	 );

 //state reset
		always @(posedge clk or posedge reset) begin
		  if(reset) begin
				state <= 0;
				correct<=0;
				incorrect<=0;
				bug<=0;
		  end
		end
		
//pinloading
		always @(posedge clk) begin
			if(reset) begin
				password <= 0;
				update<=0;
				dig_count<=0;
				verify<=0;
			end else if(firstDigit) begin
				password <= {password[6:0],digit[1]};
				secondDigit<=1;
				firstDigit<=0;
			end else if(secondDigit) begin
				password <= {password[6:0],digit[0]};
				secondDigit<=0;
				dig_count<= dig_count+1;
				update<=1;
			end else if (submit) begin
				firstDigit<=1;
			end
		end


//fsm logic
		always @(posedge clk or posedge reset) begin
		  case(state)
			0:begin//Default state
				waiting<=1;
				state <= update;
				verify<=0;
			end
			1:begin//Digit read state
				if(dig_count==4) begin//if all digits are read, move to next state
					update <= 2;
					waiting<=0;
					verify<=1;
				end else begin
					update<=0;
				end
				state <=update;		
			end
			2:begin//all digits have been read, 
			//TODO: verified timing logic with timing chart, need to decide what state 2 is.
			//Next step would be verification so i need to think about what verification logic will be and how it should relate to flags like waiting or other leds
			//waiting turns to 0 when update is assigned 2. Is this ideal? state only changes 2 cycles after update changes this should be considered.
				if(password == passkey) begin
					state <=3;
				end else begin
					state<=4;
				end
				verify<=0;
			end
			
			3:begin//correct password
				right_wrong_in<=1;
				correct<=1;
				state<=5;
				
			end
			
			4:begin//incorrect password
				right_wrong_in<=1;
				incorrect<=1;
				state<=5;
			end
			
			5:begin//Holding LED
				right_wrong_in<=0;
				if(right_wrong_out!=1) begin
					state<=0;
					correct<=0;
					incorrect<=0;
				end
					
			end
			
			default:begin
				bug<=1;
			end
		  endcase
		end


    
    

    

endmodule

DUT/Encoder.v
module priorityEncoder(
	input [3:0] in,
	output reg [1:0] out
	);
	
	
	always @(*)begin
      casez(in)
		4'b1???:out=3;
		4'b01??:out=2;
		4'b001?:out=1;
		4'b0001:out=0;
		default:begin
			out=1'bx;
			end
		endcase
	end
	
endmodule

DUT/DebitPin.v


module DebitPin #(parameter passkey = 4'b1010)(
    input digit_switches[3:0],
    input clk, reset, submit,
    output reg waiting, correct, incorrect,bug
);

    wire [1:0] digit;

    priorityEncoder priority_enc(
        .in(digit_switches),
        .out(digit)

    );

    PinCheck pinchk(
        .digit(digit),
        .submit(submit), .reset(reset), .clk(clk),
        .waiting(waiting), .correct(correct), .incorrect(incorrect),.bug(bug)
    );


endmodule

Testbench/tb_DebitPin/tb_top.sv
`ifndef passkey
    `define passkey  4'b1010
`endif


//Iverilog doesn't support constraints and random variable type :(
// class digit_item;

//     randc bit [3:0] digit;

//     constraint digit_lim {((digit == 4'b1000)||(digit == 4'b0100)||(digit == 4'b0010)||(digit == 4'b0001));}

//     function void print(string tag="");
//         $display("T=%0t [%s] digit=%0d",$time,digit);
//     endfunction
// endclass

module top();

    parameter passkey = `passkey;
   

    logic [3:0] digits;
    logic clk, reset, submit, waiting, correct, incorrect, bug;
    

    DebitPin #(passkey) debitpin(
        .digit_switches(digits),
        .clk(clk),
        .reset(reset),
        .submit(submit),
        .waiting(waiting),
        .correct(correct),
        .incorrect(incorrect),
        .bug(bug)
    );


    task DigitSubmission();//implement this testbench
        static bit [3:0] allowed_digits [0:3];
        logic [15:0] password;
        begin
            
            allowed_digits[0] = 4'b1000;
            allowed_digits[1] = 4'b0100;
            allowed_digits[2] = 4'b0010;
            allowed_digits[3] = 4'b0001;
            //for each digit
            repeat(24) begin
                password = 16'b0;

                repeat(4) begin
                    //randomize passkey selection
                    bit [3:0] digit;
                    digit = allowed_digits[$urandom_range(0, 3)];

                    //Track digits submitted
                    password = {password[11:0],digit};

                    //submit random digit
                    digits = digit;
                    @(posedge clk);
                        submit = 1;
                    @(negedge clk);
                        submit = 0;
                    //observe statemachine progression
                    $display("T=%0t,Sumbit = %0b,digits=%0b",$time,submit,digits);
                end
                assert(password ==debitpin.pinchk.password);
            end
        end

    endtask


    initial begin
        clk = 0;
        forever #5 clk = ~clk;
    end

    initial begin
        $dumpfile("dump.vcd");
        $dumpvars();
        $dumpvars(0,debitpin.pinchk);

        @(negedge clk);
            reset = 1;
        @(negedge clk);
            reset = 0;

        DigitSubmission();


        $finish();
    end

endmodule

//TODO: Correctly stores digit in top_level password shhift register- I think the submission timeline doesn't account for delay to the fsm as it doesnt update immediately in the pincheck so i need to dive into that.
//Verify clock timing on pincheck to observe if its behaving as desired based on stimulus

dump.vcd
$date
	Fri Aug 08 16:48:44 2025
$end
$version
	Icarus Verilog
$end
$timescale
	1s
$end
$scope module top $end
$var wire 1 ! waiting $end
$var wire 1 " incorrect $end
$var wire 1 # correct $end
$var wire 1 $ bug $end
$var parameter 4 % passkey $end
$var reg 1 & clk $end
$var reg 4 ' digits [3:0] $end
$var reg 1 ( reset $end
$var reg 1 ) submit $end
$scope module debitpin $end
$var wire 1 & clk $end
$var wire 4 * digit_switches [3:0] $end
$var wire 1 ( reset $end
$var wire 1 ) submit $end
$var wire 1 ! waiting $end
$var wire 1 " incorrect $end
$var wire 2 + digit [1:0] $end
$var wire 1 # correct $end
$var wire 1 $ bug $end
$var parameter 4 , passkey $end
$scope module pinchk $end
$var wire 1 & clk $end
$var wire 1 ( reset $end
$var wire 1 ) submit $end
$var wire 1 - right_wrong_out $end
$var wire 2 . digit [1:0] $end
$var parameter 4 / passkey $end
$var reg 1 $ bug $end
$var reg 1 # correct $end
$var reg 3 0 dig_count [2:0] $end
$var reg 1 1 firstDigit $end
$var reg 1 " incorrect $end
$var reg 8 2 password [7:0] $end
$var reg 1 3 right_wrong_in $end
$var reg 1 4 secondDigit $end
$var reg 3 5 state [2:0] $end
$var reg 1 6 update $end
$var reg 1 7 verify $end
$var reg 1 ! waiting $end
$scope module holdLED $end
$var wire 1 & clk $end
$var wire 1 3 reset $end
$var parameter 32 8 length $end
$var reg 1 - LED $end
$var reg 28 9 counter [27:0] $end
$upscope $end
$upscope $end
$scope module priority_enc $end
$var wire 4 : in [3:0] $end
$var reg 2 ; out [1:0] $end
$upscope $end
$upscope $end
$scope task DigitSubmission $end
$var reg 16 < password [15:0] $end
$scope begin $unm_blk_29 $end
$var reg 4 = digit [3:0] $end
$upscope $end
$upscope $end
$upscope $end
$scope module top $end
$scope module debitpin $end
$scope module pinchk $end
$scope module holdLED $end
$upscope $end
$upscope $end
$upscope $end
$upscope $end
$enddefinitions $end
$comment Show the parameter values. $end
$dumpall
b1110111001101011001010000000 8
b1010 /
b1010 ,
b1010 %
$end
#0
$dumpvars
b0 =
bx <
bx ;
bx :
bx 9
x7
x6
bx 5
x4
x3
bx 2
x1
bx 0
bx .
x-
bx +
bx *
x)
x(
bx '
0&
x$
x#
x"
x!
$end
#5
1$
0-
1&
#10
1$
0"
0#
b0 5
1(
0&
#15
0$
b0 5
1!
07
b0 0
06
b0 2
1&
#20
b1 +
b1 .
b1 ;
b10 '
b10 *
b10 :
b10 =
b10 <
0(
0&
#25
11
1)
1&
#30
b10 +
b10 .
b10 ;
b100 '
b100 *
b100 :
b100100 <
b100 =
0)
0&
#35
01
14
b1 2
1)
1&
#40
b11 +
b11 .
b11 ;
b1000 '
b1000 *
b1000 :
b1001001000 <
b1000 =
0)
0&
#45
16
b1 0
04
b11 2
1)
1&
#50
b10010010001000 <
0)
0&
#55
b1 5
11
1)
1&
#60
b1 +
b1 .
b1 ;
b10 '
b10 *
b10 :
b10 =
b10 <
0)
0&
#65
06
01
14
b110 2
1)
1&
#70
b1 '
b1 *
b1 :
b100001 <
b1 =
0)
0&
#75
b0 5
06
b10 0
04
b1101 2
1)
1&
#80
b11 +
b11 .
b11 ;
b1000 '
b1000 *
b1000 :
b1000011000 <
b1000 =
0)
0&
#85
11
1)
1&
#90
b10000110001000 <
0)
0&
#95
01
14
b11011 2
1)
1&
#100
b1 +
b1 .
b1 ;
b10 '
b10 *
b10 :
b10 =
b10 <
0)
0&
#105
16
b11 0
04
b110111 2
1)
1&
#110
b100010 <
0)
0&
#115
b1 5
11
1)
1&
#120
b1000100010 <
0)
0&
#125
06
01
14
b1101110 2
1)
1&
#130
b10001000100010 <
0)
0&
#135
b0 5
06
b100 0
04
b11011101 2
1)
1&
#140
b1 '
b1 *
b1 :
b1 =
b1 <
0)
0&
#145
11
1)
1&
#150
b10001 <
0)
0&
#155
01
14
b10111010 2
1)
1&
#160
b100010001 <
0)
0&
#165
16
b101 0
04
b1110101 2
1)
1&
#170
b10 +
b10 .
b10 ;
b100 '
b100 *
b100 :
b1000100010100 <
b100 =
0)
0&
#175
b1 5
11
1)
1&
#180
b100 <
0)
0&
#185
06
01
14
b11101011 2
1)
1&
#190
b1000100 <
0)
0&
#195
b0 5
06
b110 0
04
b11010110 2
1)
1&
#200
b1 +
b1 .
b1 ;
b1 '
b1 *
b1 :
b10001000001 <
b1 =
0)
0&
#205
11
1)
1&
#210
b11 +
b11 .
b11 ;
b1000 '
b1000 *
b1000 :
b100010000011000 <
b1000 =
0)
0&
#215
01
14
b10101101 2
1)
1&
#220
b1000 <
0)
0&
#225
16
b111 0
04
b1011011 2
1)
1&
#230
b1 +
b1 .
b1 ;
b1 '
b1 *
b1 :
b10000001 <
b1 =
0)
0&
#235
b1 5
11
1)
1&
#240
b100000010001 <
0)
0&
#245
06
01
14
b10110110 2
1)
1&
#250
b10 +
b10 .
b10 ;
b100 '
b100 *
b100 :
b1000000100010100 <
b100 =
0)
0&
#255
b0 5
06
b0 0
04
b1101100 2
1)
1&
#260
b100 <
0)
0&
#265
11
1)
1&
#270
b1000100 <
0)
0&
#275
01
14
b11011001 2
1)
1&
#280
b1 +
b1 .
b1 ;
b10 '
b10 *
b10 :
b10001000010 <
b10 =
0)
0&
#285
16
b1 0
04
b10110011 2
1)
1&
#290
b10 +
b10 .
b10 ;
b100 '
b100 *
b100 :
b100010000100100 <
b100 =
0)
0&
#295
b1 5
11
1)
1&
#300
b11 +
b11 .
b11 ;
b1000 '
b1000 *
b1000 :
b1000 =
b1000 <
0)
0&
#305
06
01
14
b1100111 2
1)
1&
#310
b10001000 <
0)
0&
#315
b0 5
06
b10 0
04
b11001111 2
1)
1&
#320
b100010001000 <
0)
0&
#325
11
1)
1&
#330
b1 +
b1 .
b1 ;
b10 '
b10 *
b10 :
b1000100010000010 <
b10 =
0)
0&
#335
01
14
b10011110 2
1)
1&
#340
b10 +
b10 .
b10 ;
b100 '
b100 *
b100 :
b100 =
b100 <
0)
0&
#345
16
b11 0
04
b111100 2
1)
1&
#350
b1 +
b1 .
b1 ;
b10 '
b10 *
b10 :
b1000010 <
b10 =
0)
0&
#355
b1 5
11
1)
1&
#360
b1 '
b1 *
b1 :
b10000100001 <
b1 =
0)
0&
#365
06
01
14
b1111000 2
1)
1&
#370
b10 +
b10 .
b10 ;
b100 '
b100 *
b100 :
b100001000010100 <
b100 =
0)
0&
#375
b0 5
06
b100 0
04
b11110000 2
1)
1&
#380
b100 <
0)
0&
#385
11
1)
1&
#390
b11 +
b11 .
b11 ;
b1000 '
b1000 *
b1000 :
b1001000 <
b1000 =
0)
0&
#395
01
14
b11100001 2
1)
1&
#400
b10010001000 <
0)
0&
#405
16
b101 0
04
b11000011 2
1)
1&
#410
b100100010001000 <
0)
0&
#415
b1 5
11
1)
1&
#420
b1 +
b1 .
b1 ;
b10 '
b10 *
b10 :
b10 =
b10 <
0)
0&
#425
06
01
14
b10000110 2
1)
1&
#430
b10 +
b10 .
b10 ;
b100 '
b100 *
b100 :
b100100 <
b100 =
0)
0&
#435
b0 5
06
b110 0
04
b1100 2
1)
1&
#440
b11 +
b11 .
b11 ;
b1000 '
b1000 *
b1000 :
b1001001000 <
b1000 =
0)
0&
#445
11
1)
1&
#450
b10 +
b10 .
b10 ;
b100 '
b100 *
b100 :
b10010010000100 <
b100 =
0)
0&
#455
01
14
b11001 2
1)
1&
#460
b1 +
b1 .
b1 ;
b10 '
b10 *
b10 :
b10 =
b10 <
0)
0&
#465
16
b111 0
04
b110011 2
1)
1&
#470
b10 +
b10 .
b10 ;
b100 '
b100 *
b100 :
b100100 <
b100 =
0)
0&
#475
b1 5
11
1)
1&
#480
b1 +
b1 .
b1 ;
b10 '
b10 *
b10 :
b1001000010 <
b10 =
0)
0&
#485
06
01
14
b1100110 2
1)
1&
#490
b10010000100010 <
0)
0&
#495
b0 5
06
b0 0
04
b11001101 2
1)
1&
#500
b10 +
b10 .
b10 ;
b100 '
b100 *
b100 :
b100 =
b100 <
0)
0&
#505
11
1)
1&
#510
b11 +
b11 .
b11 ;
b1000 '
b1000 *
b1000 :
b1001000 <
b1000 =
0)
0&
#515
01
14
b10011011 2
1)
1&
#520
b1 +
b1 .
b1 ;
b1 '
b1 *
b1 :
b10010000001 <
b1 =
0)
0&
#525
16
b1 0
04
b110111 2
1)
1&
#530
b100100000010001 <
0)
0&
#535
b1 5
11
1)
1&
#540
b10 '
b10 *
b10 :
b10 =
b10 <
0)
0&
#545
06
01
14
b1101110 2
1)
1&
#550
b10 +
b10 .
b10 ;
b100 '
b100 *
b100 :
b100100 <
b100 =
0)
0&
#555
b0 5
06
b10 0
04
b11011100 2
1)
1&
#560
b1 +
b1 .
b1 ;
b10 '
b10 *
b10 :
b1001000010 <
b10 =
0)
0&
#565
11
1)
1&
#570
b10 +
b10 .
b10 ;
b100 '
b100 *
b100 :
b10010000100100 <
b100 =
0)
0&
#575
01
14
b10111001 2
1)
1&
#580
b1 +
b1 .
b1 ;
b1 '
b1 *
b1 :
b1 =
b1 <
0)
0&
#585
16
b11 0
04
b1110011 2
1)
1&
#590
b10001 <
0)
0&
#595
b1 5
11
1)
1&
#600
b100010001 <
0)
0&
#605
06
01
14
b11100110 2
1)
1&
#610
b1000100010001 <
0)
0&
#615
b0 5
06
b100 0
04
b11001101 2
1)
1&
#620
b10 +
b10 .
b10 ;
b100 '
b100 *
b100 :
b100 =
b100 <
0)
0&
#625
11
1)
1&
#630
b1 +
b1 .
b1 ;
b10 '
b10 *
b10 :
b1000010 <
b10 =
0)
0&
#635
01
14
b10011010 2
1)
1&
#640
b11 +
b11 .
b11 ;
b1000 '
b1000 *
b1000 :
b10000101000 <
b1000 =
0)
0&
#645
16
b101 0
04
b110101 2
1)
1&
#650
b100001010001000 <
0)
0&
#655
b1 5
11
1)
1&
#660
b1 +
b1 .
b1 ;
b1 '
b1 *
b1 :
b1 =
b1 <
0)
0&
#665
06
01
14
b1101010 2
1)
1&
#670
b10 '
b10 *
b10 :
b10010 <
b10 =
0)
0&
#675
b0 5
06
b110 0
04
b11010101 2
1)
1&
#680
b11 +
b11 .
b11 ;
b1000 '
b1000 *
b1000 :
b100101000 <
b1000 =
0)
0&
#685
11
1)
1&
#690
b1 +
b1 .
b1 ;
b10 '
b10 *
b10 :
b1001010000010 <
b10 =
0)
0&
#695
01
14
b10101010 2
1)
1&
#700
b11 +
b11 .
b11 ;
b1000 '
b1000 *
b1000 :
b1000 =
b1000 <
0)
0&
#705
16
b111 0
04
b1010101 2
1)
1&
#710
b1 +
b1 .
b1 ;
b10 '
b10 *
b10 :
b10000010 <
b10 =
0)
0&
#715
b1 5
11
1)
1&
#720
b1 '
b1 *
b1 :
b100000100001 <
b1 =
0)
0&
#725
06
01
14
b10101010 2
1)
1&
#730
b1000001000010001 <
0)
0&
#735
b0 5
06
b0 0
04
b1010101 2
1)
1&
#740
b10 '
b10 *
b10 :
b10 =
b10 <
0)
0&
#745
11
1)
1&
#750
b100010 <
0)
0&
#755
01
14
b10101010 2
1)
1&
#760
b1 '
b1 *
b1 :
b1000100001 <
b1 =
0)
0&
#765
16
b1 0
04
b1010101 2
1)
1&
#770
b10001000010001 <
0)
0&
#775
b1 5
11
1)
1&
#780
b1 <
0)
0&
#785
06
01
14
b10101010 2
1)
1&
#790
b10 +
b10 .
b10 ;
b100 '
b100 *
b100 :
b10100 <
b100 =
0)
0&
#795
b0 5
06
b10 0
04
b1010100 2
1)
1&
#800
b101000100 <
0)
0&
#805
11
1)
1&
#810
b11 +
b11 .
b11 ;
b1000 '
b1000 *
b1000 :
b1010001001000 <
b1000 =
0)
0&
#815
01
14
b10101001 2
1)
1&
#820
b1000 <
0)
0&
#825
16
b11 0
04
b1010011 2
1)
1&
#830
b1 +
b1 .
b1 ;
b1 '
b1 *
b1 :
b10000001 <
b1 =
0)
0&
#835
b1 5
11
1)
1&
#840
b11 +
b11 .
b11 ;
b1000 '
b1000 *
b1000 :
b100000011000 <
b1000 =
0)
0&
#845
06
01
14
b10100111 2
1)
1&
#850
b10 +
b10 .
b10 ;
b100 '
b100 *
b100 :
b1000000110000100 <
b100 =
0)
0&
#855
b0 5
06
b100 0
04
b1001110 2
1)
1&
#860
b100 <
0)
0&
#865
11
1)
1&
#870
b11 +
b11 .
b11 ;
b1000 '
b1000 *
b1000 :
b1001000 <
b1000 =
0)
0&
#875
01
14
b10011101 2
1)
1&
#880
b1 +
b1 .
b1 ;
b1 '
b1 *
b1 :
b10010000001 <
b1 =
0)
0&
#885
16
b101 0
04
b111011 2
1)
1&
#890
b10 '
b10 *
b10 :
b100100000010010 <
b10 =
0)
0&
#895
b1 5
11
1)
1&
#900
b10 +
b10 .
b10 ;
b100 '
b100 *
b100 :
b100 =
b100 <
0)
0&
#905
06
01
14
b1110111 2
1)
1&
#910
b1 +
b1 .
b1 ;
b1 '
b1 *
b1 :
b1000001 <
b1 =
0)
0&
#915
b0 5
06
b110 0
04
b11101111 2
1)
1&
#920
b11 +
b11 .
b11 ;
b1000 '
b1000 *
b1000 :
b10000011000 <
b1000 =
0)
0&
#925
11
1)
1&
#930
b1 +
b1 .
b1 ;
b10 '
b10 *
b10 :
b100000110000010 <
b10 =
0)
0&
#935
01
14
b11011110 2
1)
1&
#940
b10 <
0)
0&
#945
16
b111 0
04
b10111101 2
1)
1&
#950
b11 +
b11 .
b11 ;
b1000 '
b1000 *
b1000 :
b101000 <
b1000 =
0)
0&
#955
b1 5
11
1)
1&
#960
b1 +
b1 .
b1 ;
b10 '
b10 *
b10 :
b1010000010 <
b10 =
0)
0&
#965
06
01
14
b1111010 2
1)
1&
#970
b10100000100010 <
0)
0&
#975
b0 5
06
b0 0
04
b11110101 2
1)
1&
#980
0)
0&
